{
  "meta": {
    "key": "hufen110v2",
    "courseTitle": "English → Hungarian",
    "scrapedAt": "2026-01-26T02:42:01.712Z",
    "sourceHash": "sha256:ab35ce810160e7f1",
    "fromLang": "English",
    "toLang": "Hungarian",
    "fromCode": "en",
    "toCode": "hu",
    "level": "CEFR INTRO",
    "levelShort": "INTRO",
    "detailHref": "https://duolingodata.com/dat/hufen110v2.html",
    "detailHrefHash": "sha256:ebc8c4f0e952e188",
    "scrapeWarnings": [],
    "schemaVersion": "1.0.0"
  },
  "totals": {
    "sections": 4,
    "activities": 3829,
    "units": 110
  },
  "sections": [
    {
      "sectionIndex": 1,
      "unitCount": 9,
      "title": "CEFR Intro:",
      "rawTitle": "CEFR Intro:",
      "cefr": "INTRO:",
      "units": [
        {
          "sectionIndex": 1,
          "unitIndex": 1,
          "title": "Name things and people",
          "activityPattern": [],
          "activities": 1
        },
        {
          "sectionIndex": 1,
          "unitIndex": 1,
          "title": "Talk about nationalities and languages",
          "activityPattern": [],
          "activities": 2
        },
        {
          "sectionIndex": 1,
          "unitIndex": 1,
          "title": "Describe people and things",
          "activityPattern": [],
          "activities": 3
        },
        {
          "sectionIndex": 1,
          "unitIndex": 1,
          "title": "Greet people",
          "activityPattern": [],
          "activities": 4
        },
        {
          "sectionIndex": 1,
          "unitIndex": 1,
          "title": "Say where people and things are",
          "activityPattern": [],
          "activities": 5
        },
        {
          "sectionIndex": 1,
          "unitIndex": 1,
          "title": "Communicate at school",
          "activityPattern": [],
          "activities": 6
        },
        {
          "sectionIndex": 1,
          "unitIndex": 1,
          "title": "Use verbs in present tense",
          "activityPattern": [],
          "activities": 7
        },
        {
          "sectionIndex": 1,
          "unitIndex": 1,
          "title": "Talk about food and drink",
          "activityPattern": [],
          "activities": 8
        },
        {
          "sectionIndex": 1,
          "unitIndex": 1,
          "title": "Express feelings",
          "activityPattern": [],
          "activities": 9
        }
      ]
    },
    {
      "sectionIndex": 2,
      "unitCount": 30,
      "title": ":",
      "rawTitle": "CEFR A1:",
      "cefr": "A1",
      "units": [
        {
          "sectionIndex": 2,
          "unitIndex": 2,
          "title": "Identify professions",
          "activityPattern": [],
          "activities": 1
        },
        {
          "sectionIndex": 2,
          "unitIndex": 2,
          "title": "Talk about cooking and eating",
          "activityPattern": [],
          "activities": 2
        },
        {
          "sectionIndex": 2,
          "unitIndex": 2,
          "title": "Form the plural of nouns",
          "activityPattern": [],
          "activities": 3
        },
        {
          "sectionIndex": 2,
          "unitIndex": 2,
          "title": "Express quantities",
          "activityPattern": [],
          "activities": 4
        },
        {
          "sectionIndex": 2,
          "unitIndex": 2,
          "title": "Say what we and they do",
          "activityPattern": [],
          "activities": 5
        },
        {
          "sectionIndex": 2,
          "unitIndex": 2,
          "title": "Locate places in a city",
          "activityPattern": [],
          "activities": 6
        },
        {
          "sectionIndex": 2,
          "unitIndex": 2,
          "title": "Use the verbs come and go",
          "activityPattern": [],
          "activities": 7
        },
        {
          "sectionIndex": 2,
          "unitIndex": 2,
          "title": "Tell time",
          "activityPattern": [],
          "activities": 8
        },
        {
          "sectionIndex": 2,
          "unitIndex": 2,
          "title": "Use different forms of this and that",
          "activityPattern": [],
          "activities": 9
        },
        {
          "sectionIndex": 2,
          "unitIndex": 2,
          "title": "Talk about schedules",
          "activityPattern": [],
          "activities": 10
        },
        {
          "sectionIndex": 2,
          "unitIndex": 2,
          "title": "Shop for clothes",
          "activityPattern": [],
          "activities": 11
        },
        {
          "sectionIndex": 2,
          "unitIndex": 2,
          "title": "Talk about hobbies and habits",
          "activityPattern": [],
          "activities": 12
        },
        {
          "sectionIndex": 2,
          "unitIndex": 2,
          "title": "Indicate the location",
          "activityPattern": [],
          "activities": 13
        },
        {
          "sectionIndex": 2,
          "unitIndex": 2,
          "title": "Describe things and people",
          "activityPattern": [],
          "activities": 14
        },
        {
          "sectionIndex": 2,
          "unitIndex": 2,
          "title": "Use van and nincs",
          "activityPattern": [],
          "activities": 15
        },
        {
          "sectionIndex": 2,
          "unitIndex": 2,
          "title": "Talk about the weather",
          "activityPattern": [],
          "activities": 16
        },
        {
          "sectionIndex": 2,
          "unitIndex": 2,
          "title": "Form the possessive",
          "activityPattern": [],
          "activities": 17
        },
        {
          "sectionIndex": 2,
          "unitIndex": 2,
          "title": "Name nationalities",
          "activityPattern": [],
          "activities": 18
        },
        {
          "sectionIndex": 2,
          "unitIndex": 2,
          "title": "Form direct objects",
          "activityPattern": [],
          "activities": 19
        },
        {
          "sectionIndex": 2,
          "unitIndex": 2,
          "title": "Describe health issues",
          "activityPattern": [],
          "activities": 20
        },
        {
          "sectionIndex": 2,
          "unitIndex": 2,
          "title": "Express quantity",
          "activityPattern": [],
          "activities": 21
        },
        {
          "sectionIndex": 2,
          "unitIndex": 2,
          "title": "Use definite verb forms",
          "activityPattern": [],
          "activities": 22
        },
        {
          "sectionIndex": 2,
          "unitIndex": 2,
          "title": "Talk about your family",
          "activityPattern": [],
          "activities": 23
        },
        {
          "sectionIndex": 2,
          "unitIndex": 2,
          "title": "Discuss everyday activities",
          "activityPattern": [],
          "activities": 24
        },
        {
          "sectionIndex": 2,
          "unitIndex": 2,
          "title": "Refer to you and me",
          "activityPattern": [],
          "activities": 25
        },
        {
          "sectionIndex": 2,
          "unitIndex": 2,
          "title": "Say what people are doing",
          "activityPattern": [],
          "activities": 26
        },
        {
          "sectionIndex": 2,
          "unitIndex": 2,
          "title": "Express emotions",
          "activityPattern": [],
          "activities": 27
        },
        {
          "sectionIndex": 2,
          "unitIndex": 2,
          "title": "Say what languages you speak",
          "activityPattern": [],
          "activities": 28
        },
        {
          "sectionIndex": 2,
          "unitIndex": 2,
          "title": "Use direct objects in plural form",
          "activityPattern": [],
          "activities": 29
        },
        {
          "sectionIndex": 2,
          "unitIndex": 2,
          "title": "Talk about activities",
          "activityPattern": [],
          "activities": 30
        }
      ]
    },
    {
      "sectionIndex": 3,
      "unitCount": 30,
      "title": ":",
      "rawTitle": "CEFR A1:",
      "cefr": "A1",
      "units": [
        {
          "sectionIndex": 3,
          "unitIndex": 3,
          "title": "Ask about directions",
          "activityPattern": [],
          "activities": 1
        },
        {
          "sectionIndex": 3,
          "unitIndex": 3,
          "title": "Order food",
          "activityPattern": [],
          "activities": 2
        },
        {
          "sectionIndex": 3,
          "unitIndex": 3,
          "title": "Talk about what you have",
          "activityPattern": [],
          "activities": 3
        },
        {
          "sectionIndex": 3,
          "unitIndex": 3,
          "title": "Express actions",
          "activityPattern": [],
          "activities": 4
        },
        {
          "sectionIndex": 3,
          "unitIndex": 3,
          "title": "Talk about giving someone something",
          "activityPattern": [],
          "activities": 5
        },
        {
          "sectionIndex": 3,
          "unitIndex": 3,
          "title": "Describe things and people",
          "activityPattern": [],
          "activities": 6
        },
        {
          "sectionIndex": 3,
          "unitIndex": 3,
          "title": "Talk about art activities",
          "activityPattern": [],
          "activities": 7
        },
        {
          "sectionIndex": 3,
          "unitIndex": 3,
          "title": "Comment on sports",
          "activityPattern": [],
          "activities": 8
        },
        {
          "sectionIndex": 3,
          "unitIndex": 3,
          "title": "Talk about being inside",
          "activityPattern": [],
          "activities": 9
        },
        {
          "sectionIndex": 3,
          "unitIndex": 3,
          "title": "Say what and who is beside something else",
          "activityPattern": [],
          "activities": 10
        },
        {
          "sectionIndex": 3,
          "unitIndex": 3,
          "title": "Describe outfits",
          "activityPattern": [],
          "activities": 11
        },
        {
          "sectionIndex": 3,
          "unitIndex": 3,
          "title": "Talk about your home",
          "activityPattern": [],
          "activities": 12
        },
        {
          "sectionIndex": 3,
          "unitIndex": 3,
          "title": "Discuss possession",
          "activityPattern": [],
          "activities": 13
        },
        {
          "sectionIndex": 3,
          "unitIndex": 3,
          "title": "Compare things and people",
          "activityPattern": [],
          "activities": 14
        },
        {
          "sectionIndex": 3,
          "unitIndex": 3,
          "title": "Express dates and times",
          "activityPattern": [],
          "activities": 15
        },
        {
          "sectionIndex": 3,
          "unitIndex": 3,
          "title": "Talk about technology",
          "activityPattern": [],
          "activities": 16
        },
        {
          "sectionIndex": 3,
          "unitIndex": 3,
          "title": "Use different forms of this and that",
          "activityPattern": [],
          "activities": 17
        },
        {
          "sectionIndex": 3,
          "unitIndex": 3,
          "title": "Talk about celebrations",
          "activityPattern": [],
          "activities": 18
        },
        {
          "sectionIndex": 3,
          "unitIndex": 3,
          "title": "Describe past events",
          "activityPattern": [],
          "activities": 19
        },
        {
          "sectionIndex": 3,
          "unitIndex": 3,
          "title": "Talk about animals",
          "activityPattern": [],
          "activities": 20
        },
        {
          "sectionIndex": 3,
          "unitIndex": 3,
          "title": "Say who you do things with",
          "activityPattern": [],
          "activities": 21
        },
        {
          "sectionIndex": 3,
          "unitIndex": 3,
          "title": "Talk about colors",
          "activityPattern": [],
          "activities": 22
        },
        {
          "sectionIndex": 3,
          "unitIndex": 3,
          "title": "Use ordinal numbers",
          "activityPattern": [],
          "activities": 23
        },
        {
          "sectionIndex": 3,
          "unitIndex": 3,
          "title": "Make negative statements",
          "activityPattern": [],
          "activities": 24
        },
        {
          "sectionIndex": 3,
          "unitIndex": 3,
          "title": "Say what others have",
          "activityPattern": [],
          "activities": 25
        },
        {
          "sectionIndex": 3,
          "unitIndex": 3,
          "title": "Distinguish past and present",
          "activityPattern": [],
          "activities": 26
        },
        {
          "sectionIndex": 3,
          "unitIndex": 3,
          "title": "Describe movement into",
          "activityPattern": [],
          "activities": 27
        },
        {
          "sectionIndex": 3,
          "unitIndex": 3,
          "title": "Discuss direction",
          "activityPattern": [],
          "activities": 28
        },
        {
          "sectionIndex": 3,
          "unitIndex": 3,
          "title": "Describe movement toward",
          "activityPattern": [],
          "activities": 29
        },
        {
          "sectionIndex": 3,
          "unitIndex": 3,
          "title": "Clarify directions",
          "activityPattern": [],
          "activities": 30
        }
      ]
    },
    {
      "sectionIndex": 4,
      "unitCount": 41,
      "title": ":",
      "rawTitle": "CEFR A2:",
      "cefr": "A2",
      "units": [
        {
          "sectionIndex": 4,
          "unitIndex": 4,
          "title": "Use verbal prefixes in negative sentences",
          "activityPattern": [],
          "activities": 1
        },
        {
          "sectionIndex": 4,
          "unitIndex": 4,
          "title": "Indicate movement into places",
          "activityPattern": [],
          "activities": 2
        },
        {
          "sectionIndex": 4,
          "unitIndex": 4,
          "title": "Describe direction",
          "activityPattern": [],
          "activities": 3
        },
        {
          "sectionIndex": 4,
          "unitIndex": 4,
          "title": "Describe movement toward a place",
          "activityPattern": [],
          "activities": 4
        },
        {
          "sectionIndex": 4,
          "unitIndex": 4,
          "title": "State geography facts",
          "activityPattern": [],
          "activities": 5
        },
        {
          "sectionIndex": 4,
          "unitIndex": 4,
          "title": "Make statements about the past",
          "activityPattern": [],
          "activities": 6
        },
        {
          "sectionIndex": 4,
          "unitIndex": 4,
          "title": "Form complex sentences",
          "activityPattern": [],
          "activities": 7
        },
        {
          "sectionIndex": 4,
          "unitIndex": 4,
          "title": "Discuss choices",
          "activityPattern": [],
          "activities": 8
        },
        {
          "sectionIndex": 4,
          "unitIndex": 4,
          "title": "Talk about experiences and changes",
          "activityPattern": [],
          "activities": 9
        },
        {
          "sectionIndex": 4,
          "unitIndex": 4,
          "title": "Describe things and people",
          "activityPattern": [],
          "activities": 10
        },
        {
          "sectionIndex": 4,
          "unitIndex": 4,
          "title": "Use verbal prefixes",
          "activityPattern": [],
          "activities": 11
        },
        {
          "sectionIndex": 4,
          "unitIndex": 4,
          "title": "Talk about travel",
          "activityPattern": [],
          "activities": 12
        },
        {
          "sectionIndex": 4,
          "unitIndex": 4,
          "title": "Say what happened",
          "activityPattern": [],
          "activities": 13
        },
        {
          "sectionIndex": 4,
          "unitIndex": 4,
          "title": "Discuss origins",
          "activityPattern": [],
          "activities": 14
        },
        {
          "sectionIndex": 4,
          "unitIndex": 4,
          "title": "Indicate the starting point",
          "activityPattern": [],
          "activities": 15
        },
        {
          "sectionIndex": 4,
          "unitIndex": 4,
          "title": "Describe distances",
          "activityPattern": [],
          "activities": 16
        },
        {
          "sectionIndex": 4,
          "unitIndex": 4,
          "title": "Combine postpositions with this and that",
          "activityPattern": [],
          "activities": 17
        },
        {
          "sectionIndex": 4,
          "unitIndex": 4,
          "title": "Discuss future plans",
          "activityPattern": [],
          "activities": 18
        },
        {
          "sectionIndex": 4,
          "unitIndex": 4,
          "title": "Talk about neighbors and friends",
          "activityPattern": [],
          "activities": 19
        },
        {
          "sectionIndex": 4,
          "unitIndex": 4,
          "title": "Clarify locations",
          "activityPattern": [],
          "activities": 20
        },
        {
          "sectionIndex": 4,
          "unitIndex": 4,
          "title": "Talk about cooking and eating",
          "activityPattern": [],
          "activities": 21
        },
        {
          "sectionIndex": 4,
          "unitIndex": 4,
          "title": "Discover a city",
          "activityPattern": [],
          "activities": 22
        },
        {
          "sectionIndex": 4,
          "unitIndex": 4,
          "title": "Ask about directions",
          "activityPattern": [],
          "activities": 23
        },
        {
          "sectionIndex": 4,
          "unitIndex": 4,
          "title": "Talk about the past",
          "activityPattern": [],
          "activities": 24
        },
        {
          "sectionIndex": 4,
          "unitIndex": 4,
          "title": "Use relative pronouns",
          "activityPattern": [],
          "activities": 25
        },
        {
          "sectionIndex": 4,
          "unitIndex": 4,
          "title": "Talk about belongings",
          "activityPattern": [],
          "activities": 26
        },
        {
          "sectionIndex": 4,
          "unitIndex": 4,
          "title": "Make calculations",
          "activityPattern": [],
          "activities": 27
        },
        {
          "sectionIndex": 4,
          "unitIndex": 4,
          "title": "Use everybody and somebody",
          "activityPattern": [],
          "activities": 28
        },
        {
          "sectionIndex": 4,
          "unitIndex": 4,
          "title": "Use everywhere and somewhere",
          "activityPattern": [],
          "activities": 29
        },
        {
          "sectionIndex": 4,
          "unitIndex": 4,
          "title": "Describe what people have",
          "activityPattern": [],
          "activities": 30
        },
        {
          "sectionIndex": 4,
          "unitIndex": 4,
          "title": "Use different forms of this and that",
          "activityPattern": [],
          "activities": 31
        },
        {
          "sectionIndex": 4,
          "unitIndex": 4,
          "title": "Combine suffixes",
          "activityPattern": [],
          "activities": 32
        },
        {
          "sectionIndex": 4,
          "unitIndex": 4,
          "title": "Indicate the starting point",
          "activityPattern": [],
          "activities": 33
        },
        {
          "sectionIndex": 4,
          "unitIndex": 4,
          "title": "Talk about position",
          "activityPattern": [],
          "activities": 34
        },
        {
          "sectionIndex": 4,
          "unitIndex": 4,
          "title": "Use postpositions",
          "activityPattern": [],
          "activities": 35
        },
        {
          "sectionIndex": 4,
          "unitIndex": 4,
          "title": "Form plural possessives",
          "activityPattern": [],
          "activities": 36
        },
        {
          "sectionIndex": 4,
          "unitIndex": 4,
          "title": "Tell others what to do",
          "activityPattern": [],
          "activities": 37
        },
        {
          "sectionIndex": 4,
          "unitIndex": 4,
          "title": "Talk about how many",
          "activityPattern": [],
          "activities": 38
        },
        {
          "sectionIndex": 4,
          "unitIndex": 4,
          "title": "Use verb conjugations",
          "activityPattern": [],
          "activities": 39
        },
        {
          "sectionIndex": 4,
          "unitIndex": 4,
          "title": "Express opinions",
          "activityPattern": [],
          "activities": 40
        },
        {
          "sectionIndex": 4,
          "unitIndex": 4,
          "title": "Combine suffixes",
          "activityPattern": [
            2025,
            9
          ],
          "activities": 2034
        }
      ]
    }
  ]
}