{
  "meta": {
    "key": "ptfid131",
    "courseTitle": "Indonesian → Portuguese",
    "scrapedAt": "2026-01-26T02:42:01.712Z",
    "sourceHash": "sha256:78fbe37aad8d7040",
    "fromLang": "Indonesian",
    "toLang": "Portuguese",
    "fromCode": "id",
    "toCode": "pt",
    "level": "CEFR INTRO",
    "levelShort": "INTRO",
    "detailHref": "https://duolingodata.com/dat/ptfid131.html",
    "detailHrefHash": "sha256:f1f3eb77d2d58720",
    "scrapeWarnings": [],
    "schemaVersion": "1.0.0"
  },
  "totals": {
    "sections": 4,
    "activities": 4808,
    "units": 131
  },
  "sections": [
    {
      "sectionIndex": 1,
      "unitCount": 11,
      "title": "CEFR Intro:",
      "rawTitle": "CEFR Intro:",
      "cefr": "INTRO:",
      "units": [
        {
          "sectionIndex": 1,
          "unitIndex": 1,
          "title": "Memesan di kafe",
          "activityPattern": [],
          "activities": 1
        },
        {
          "sectionIndex": 1,
          "unitIndex": 1,
          "title": "Menyapa dan mengucapkan selamat tinggal",
          "activityPattern": [],
          "activities": 2
        },
        {
          "sectionIndex": 1,
          "unitIndex": 1,
          "title": "Menceritakan asal usul",
          "activityPattern": [],
          "activities": 3
        },
        {
          "sectionIndex": 1,
          "unitIndex": 1,
          "title": "Mengenali anggota keluarga",
          "activityPattern": [],
          "activities": 4
        },
        {
          "sectionIndex": 1,
          "unitIndex": 1,
          "title": "Mendeskripsikan sifat karakter",
          "activityPattern": [],
          "activities": 5
        },
        {
          "sectionIndex": 1,
          "unitIndex": 1,
          "title": "Menemukan barang-barang",
          "activityPattern": [],
          "activities": 6
        },
        {
          "sectionIndex": 1,
          "unitIndex": 1,
          "title": "Menemukan tempat di kota",
          "activityPattern": [],
          "activities": 7
        },
        {
          "sectionIndex": 1,
          "unitIndex": 1,
          "title": "Menggunakan kata kerja bentuk sekarang",
          "activityPattern": [],
          "activities": 8
        },
        {
          "sectionIndex": 1,
          "unitIndex": 1,
          "title": "Membicarakan tentang cuaca",
          "activityPattern": [],
          "activities": 9
        },
        {
          "sectionIndex": 1,
          "unitIndex": 1,
          "title": "Belanja kebutuhan sehari-hari",
          "activityPattern": [],
          "activities": 10
        },
        {
          "sectionIndex": 1,
          "unitIndex": 1,
          "title": "Mendeskripsikan rumah",
          "activityPattern": [],
          "activities": 11
        }
      ]
    },
    {
      "sectionIndex": 2,
      "unitCount": 30,
      "title": ":",
      "rawTitle": "CEFR A1:",
      "cefr": "A1",
      "units": [
        {
          "sectionIndex": 2,
          "unitIndex": 2,
          "title": "Menggunakan kata kerja bentuk sekarang",
          "activityPattern": [],
          "activities": 1
        },
        {
          "sectionIndex": 2,
          "unitIndex": 2,
          "title": "Mendiskusikan kegiatan olahraga",
          "activityPattern": [],
          "activities": 2
        },
        {
          "sectionIndex": 2,
          "unitIndex": 2,
          "title": "Membicarakan tentang hobi",
          "activityPattern": [],
          "activities": 3
        },
        {
          "sectionIndex": 2,
          "unitIndex": 2,
          "title": "Mengikuti kelas",
          "activityPattern": [],
          "activities": 4
        },
        {
          "sectionIndex": 2,
          "unitIndex": 2,
          "title": "Memesan makanan dan minuman",
          "activityPattern": [],
          "activities": 5
        },
        {
          "sectionIndex": 2,
          "unitIndex": 2,
          "title": "Mengulas makanan dan layanan",
          "activityPattern": [],
          "activities": 6
        },
        {
          "sectionIndex": 2,
          "unitIndex": 2,
          "title": "Menemukan jalan",
          "activityPattern": [],
          "activities": 7
        },
        {
          "sectionIndex": 2,
          "unitIndex": 2,
          "title": "Kesepakatan gender dan jumlah",
          "activityPattern": [],
          "activities": 8
        },
        {
          "sectionIndex": 2,
          "unitIndex": 2,
          "title": "Membicarakan tentang tempat kerja",
          "activityPattern": [],
          "activities": 9
        },
        {
          "sectionIndex": 2,
          "unitIndex": 2,
          "title": "Belanja kebutuhan sehari-hari",
          "activityPattern": [],
          "activities": 10
        },
        {
          "sectionIndex": 2,
          "unitIndex": 2,
          "title": "Menggunakan kata sifat kepemilikan",
          "activityPattern": [],
          "activities": 11
        },
        {
          "sectionIndex": 2,
          "unitIndex": 2,
          "title": "Mengenali barang-barang di kelas",
          "activityPattern": [],
          "activities": 12
        },
        {
          "sectionIndex": 2,
          "unitIndex": 2,
          "title": "Bertanya tentang perasaan",
          "activityPattern": [],
          "activities": 13
        },
        {
          "sectionIndex": 2,
          "unitIndex": 2,
          "title": "Menanyakan arah jalan",
          "activityPattern": [],
          "activities": 14
        },
        {
          "sectionIndex": 2,
          "unitIndex": 2,
          "title": "Menggunakan kata jumlah dalam pertanyaan",
          "activityPattern": [],
          "activities": 15
        },
        {
          "sectionIndex": 2,
          "unitIndex": 2,
          "title": "Berkenalan dengan orang baru",
          "activityPattern": [],
          "activities": 16
        },
        {
          "sectionIndex": 2,
          "unitIndex": 2,
          "title": "Mendeskripsikan anggota keluarga",
          "activityPattern": [],
          "activities": 17
        },
        {
          "sectionIndex": 2,
          "unitIndex": 2,
          "title": "Merencanakan jadwal",
          "activityPattern": [],
          "activities": 18
        },
        {
          "sectionIndex": 2,
          "unitIndex": 2,
          "title": "Menggunakan sapaan formal",
          "activityPattern": [],
          "activities": 19
        },
        {
          "sectionIndex": 2,
          "unitIndex": 2,
          "title": "Membagikan cerita pribadi",
          "activityPattern": [],
          "activities": 20
        },
        {
          "sectionIndex": 2,
          "unitIndex": 2,
          "title": "Menggunakan kata kerja bentuk sekarang",
          "activityPattern": [],
          "activities": 21
        },
        {
          "sectionIndex": 2,
          "unitIndex": 2,
          "title": "Mendiskusikan hewan dan habitatnya",
          "activityPattern": [],
          "activities": 22
        },
        {
          "sectionIndex": 2,
          "unitIndex": 2,
          "title": "Mendeskripsikan rutinitas harian",
          "activityPattern": [],
          "activities": 23
        },
        {
          "sectionIndex": 2,
          "unitIndex": 2,
          "title": "Menggunakan kata kerja refleksif",
          "activityPattern": [],
          "activities": 24
        },
        {
          "sectionIndex": 2,
          "unitIndex": 2,
          "title": "Mendiskusikan hobi",
          "activityPattern": [],
          "activities": 25
        },
        {
          "sectionIndex": 2,
          "unitIndex": 2,
          "title": "Membicarakan tentang acara musik",
          "activityPattern": [],
          "activities": 26
        },
        {
          "sectionIndex": 2,
          "unitIndex": 2,
          "title": "Mendiskusikan kegiatan santai",
          "activityPattern": [],
          "activities": 27
        },
        {
          "sectionIndex": 2,
          "unitIndex": 2,
          "title": "Meminta bantuan medis",
          "activityPattern": [],
          "activities": 28
        },
        {
          "sectionIndex": 2,
          "unitIndex": 2,
          "title": "Mendiskusikan perjalanan",
          "activityPattern": [],
          "activities": 29
        },
        {
          "sectionIndex": 2,
          "unitIndex": 2,
          "title": "Membicarakan tentang ulang tahun",
          "activityPattern": [],
          "activities": 30
        }
      ]
    },
    {
      "sectionIndex": 3,
      "unitCount": 30,
      "title": ":",
      "rawTitle": "CEFR A1:",
      "cefr": "A1",
      "units": [
        {
          "sectionIndex": 3,
          "unitIndex": 3,
          "title": "Menyatakan preferensi dan keinginan",
          "activityPattern": [],
          "activities": 1
        },
        {
          "sectionIndex": 3,
          "unitIndex": 3,
          "title": "Membicarakan tentang pergi keluar",
          "activityPattern": [],
          "activities": 2
        },
        {
          "sectionIndex": 3,
          "unitIndex": 3,
          "title": "Merencanakan aktivitas kebugaran",
          "activityPattern": [],
          "activities": 3
        },
        {
          "sectionIndex": 3,
          "unitIndex": 3,
          "title": "Menyatakan kebutuhan dan keinginan",
          "activityPattern": [],
          "activities": 4
        },
        {
          "sectionIndex": 3,
          "unitIndex": 3,
          "title": "Merencanakan perjalanan",
          "activityPattern": [],
          "activities": 5
        },
        {
          "sectionIndex": 3,
          "unitIndex": 3,
          "title": "Menyatakan tindakan segera",
          "activityPattern": [],
          "activities": 6
        },
        {
          "sectionIndex": 3,
          "unitIndex": 3,
          "title": "Menjelajahi kota",
          "activityPattern": [],
          "activities": 7
        },
        {
          "sectionIndex": 3,
          "unitIndex": 3,
          "title": "Menggunakan kata tunjuk",
          "activityPattern": [],
          "activities": 8
        },
        {
          "sectionIndex": 3,
          "unitIndex": 3,
          "title": "Mencari bahan-bahan makanan",
          "activityPattern": [],
          "activities": 9
        },
        {
          "sectionIndex": 3,
          "unitIndex": 3,
          "title": "Merayakan bersama teman-teman",
          "activityPattern": [],
          "activities": 10
        },
        {
          "sectionIndex": 3,
          "unitIndex": 3,
          "title": "Belanja pakaian",
          "activityPattern": [],
          "activities": 11
        },
        {
          "sectionIndex": 3,
          "unitIndex": 3,
          "title": "Kata kerja sekarang untuk rutinitas",
          "activityPattern": [],
          "activities": 12
        },
        {
          "sectionIndex": 3,
          "unitIndex": 3,
          "title": "Mendiskusikan masalah kesehatan",
          "activityPattern": [],
          "activities": 13
        },
        {
          "sectionIndex": 3,
          "unitIndex": 3,
          "title": "Kata ganti dan kata sifat tak tentu",
          "activityPattern": [],
          "activities": 14
        },
        {
          "sectionIndex": 3,
          "unitIndex": 3,
          "title": "Menangani masalah di tempat kerja",
          "activityPattern": [],
          "activities": 15
        },
        {
          "sectionIndex": 3,
          "unitIndex": 3,
          "title": "Menggunakan kata tunjuk",
          "activityPattern": [],
          "activities": 16
        },
        {
          "sectionIndex": 3,
          "unitIndex": 3,
          "title": "Mendiskusikan film",
          "activityPattern": [],
          "activities": 17
        },
        {
          "sectionIndex": 3,
          "unitIndex": 3,
          "title": "Mengikuti kegiatan",
          "activityPattern": [],
          "activities": 18
        },
        {
          "sectionIndex": 3,
          "unitIndex": 3,
          "title": "Mengirim dan menerima surat",
          "activityPattern": [],
          "activities": 19
        },
        {
          "sectionIndex": 3,
          "unitIndex": 3,
          "title": "Kata kerja yang masih berlangsung",
          "activityPattern": [],
          "activities": 20
        },
        {
          "sectionIndex": 3,
          "unitIndex": 3,
          "title": "Membicarakan tentang cuaca",
          "activityPattern": [],
          "activities": 21
        },
        {
          "sectionIndex": 3,
          "unitIndex": 3,
          "title": "Mendiskusikan tekanan di tempat kerja",
          "activityPattern": [],
          "activities": 22
        },
        {
          "sectionIndex": 3,
          "unitIndex": 3,
          "title": "Menggunakan kata keterangan",
          "activityPattern": [],
          "activities": 23
        },
        {
          "sectionIndex": 3,
          "unitIndex": 3,
          "title": "Menggunakan kata jumlah",
          "activityPattern": [],
          "activities": 24
        },
        {
          "sectionIndex": 3,
          "unitIndex": 3,
          "title": "Mengobrol online",
          "activityPattern": [],
          "activities": 25
        },
        {
          "sectionIndex": 3,
          "unitIndex": 3,
          "title": "Menikmati olahraga dan permainan",
          "activityPattern": [],
          "activities": 26
        },
        {
          "sectionIndex": 3,
          "unitIndex": 3,
          "title": "Melakukan pekerjaan rumah tangga",
          "activityPattern": [],
          "activities": 27
        },
        {
          "sectionIndex": 3,
          "unitIndex": 3,
          "title": "Menangani keadaan darurat",
          "activityPattern": [],
          "activities": 28
        },
        {
          "sectionIndex": 3,
          "unitIndex": 3,
          "title": "Kata kerja modal untuk kebutuhan & izin",
          "activityPattern": [],
          "activities": 29
        },
        {
          "sectionIndex": 3,
          "unitIndex": 3,
          "title": "Bekerja di kantor",
          "activityPattern": [],
          "activities": 30
        }
      ]
    },
    {
      "sectionIndex": 4,
      "unitCount": 60,
      "title": ":",
      "rawTitle": "CEFR A2:",
      "cefr": "A2",
      "units": [
        {
          "sectionIndex": 4,
          "unitIndex": 4,
          "title": "Mendiskusikan rencana besok",
          "activityPattern": [],
          "activities": 1
        },
        {
          "sectionIndex": 4,
          "unitIndex": 4,
          "title": "Menjelaskan masalah teknis dengan sopan",
          "activityPattern": [],
          "activities": 2
        },
        {
          "sectionIndex": 4,
          "unitIndex": 4,
          "title": "Membahas tentang pengamatan di kota",
          "activityPattern": [],
          "activities": 3
        },
        {
          "sectionIndex": 4,
          "unitIndex": 4,
          "title": "Mendiskusikan film favorit",
          "activityPattern": [],
          "activities": 4
        },
        {
          "sectionIndex": 4,
          "unitIndex": 4,
          "title": "Mendeskripsikan anggota keluarga",
          "activityPattern": [],
          "activities": 5
        },
        {
          "sectionIndex": 4,
          "unitIndex": 4,
          "title": "Mendeskripsikan selebritas",
          "activityPattern": [],
          "activities": 6
        },
        {
          "sectionIndex": 4,
          "unitIndex": 4,
          "title": "Membahas masalah ketepatan waktu rapat",
          "activityPattern": [],
          "activities": 7
        },
        {
          "sectionIndex": 4,
          "unitIndex": 4,
          "title": "Membahas insiden pernikahan",
          "activityPattern": [],
          "activities": 8
        },
        {
          "sectionIndex": 4,
          "unitIndex": 4,
          "title": "Menjelaskan tugas sukarelawan",
          "activityPattern": [],
          "activities": 9
        },
        {
          "sectionIndex": 4,
          "unitIndex": 4,
          "title": "Menanyakan barang hilang",
          "activityPattern": [],
          "activities": 10
        },
        {
          "sectionIndex": 4,
          "unitIndex": 4,
          "title": "Membeli sayur di pasar",
          "activityPattern": [],
          "activities": 11
        },
        {
          "sectionIndex": 4,
          "unitIndex": 4,
          "title": "Bertukar kado dengan keluarga",
          "activityPattern": [],
          "activities": 12
        },
        {
          "sectionIndex": 4,
          "unitIndex": 4,
          "title": "Menanyakan bahan masakan",
          "activityPattern": [],
          "activities": 13
        },
        {
          "sectionIndex": 4,
          "unitIndex": 4,
          "title": "Mendiskusikan acara pernikahan",
          "activityPattern": [],
          "activities": 14
        },
        {
          "sectionIndex": 4,
          "unitIndex": 4,
          "title": "Mendiskusikan sewa rumah",
          "activityPattern": [],
          "activities": 15
        },
        {
          "sectionIndex": 4,
          "unitIndex": 4,
          "title": "Meminta informasi proyek dengan sopan",
          "activityPattern": [],
          "activities": 16
        },
        {
          "sectionIndex": 4,
          "unitIndex": 4,
          "title": "Menceritakan pengalaman kencan",
          "activityPattern": [],
          "activities": 17
        },
        {
          "sectionIndex": 4,
          "unitIndex": 4,
          "title": "Menanyakan arah dengan sopan",
          "activityPattern": [],
          "activities": 18
        },
        {
          "sectionIndex": 4,
          "unitIndex": 4,
          "title": "Membahas pemulihan bersama dokter",
          "activityPattern": [],
          "activities": 19
        },
        {
          "sectionIndex": 4,
          "unitIndex": 4,
          "title": "Berkomunikasi dengan anggota tim",
          "activityPattern": [],
          "activities": 20
        },
        {
          "sectionIndex": 4,
          "unitIndex": 4,
          "title": "Memberi perintah untuk tugas rumah",
          "activityPattern": [],
          "activities": 21
        },
        {
          "sectionIndex": 4,
          "unitIndex": 4,
          "title": "Menceritakan sejarah keluarga",
          "activityPattern": [],
          "activities": 22
        },
        {
          "sectionIndex": 4,
          "unitIndex": 4,
          "title": "Membahas kenangan belanja masa kecil",
          "activityPattern": [],
          "activities": 23
        },
        {
          "sectionIndex": 4,
          "unitIndex": 4,
          "title": "Menceritakan pengalaman masa lalu",
          "activityPattern": [],
          "activities": 24
        },
        {
          "sectionIndex": 4,
          "unitIndex": 4,
          "title": "Menyewa atau membeli rumah",
          "activityPattern": [],
          "activities": 25
        },
        {
          "sectionIndex": 4,
          "unitIndex": 4,
          "title": "Merencanakan tur keliling taman",
          "activityPattern": [],
          "activities": 26
        },
        {
          "sectionIndex": 4,
          "unitIndex": 4,
          "title": "Membahas tentang pengalaman masa lalu",
          "activityPattern": [],
          "activities": 27
        },
        {
          "sectionIndex": 4,
          "unitIndex": 4,
          "title": "Menceritakan riwayat hidup",
          "activityPattern": [],
          "activities": 28
        },
        {
          "sectionIndex": 4,
          "unitIndex": 4,
          "title": "Mendiskusikan pengalaman kerja",
          "activityPattern": [],
          "activities": 29
        },
        {
          "sectionIndex": 4,
          "unitIndex": 4,
          "title": "Mengirim pesan ke teman",
          "activityPattern": [],
          "activities": 30
        },
        {
          "sectionIndex": 4,
          "unitIndex": 4,
          "title": "Berbagi pendapat tentang tren kesehatan",
          "activityPattern": [],
          "activities": 31
        },
        {
          "sectionIndex": 4,
          "unitIndex": 4,
          "title": "Menceritakan kebiasaan masa lalu",
          "activityPattern": [],
          "activities": 32
        },
        {
          "sectionIndex": 4,
          "unitIndex": 4,
          "title": "Mendiskusikan aktivitas dulu dan kini",
          "activityPattern": [],
          "activities": 33
        },
        {
          "sectionIndex": 4,
          "unitIndex": 4,
          "title": "Merayakan prestasi dalam acara",
          "activityPattern": [],
          "activities": 34
        },
        {
          "sectionIndex": 4,
          "unitIndex": 4,
          "title": "Mendeskripsikan furnitur",
          "activityPattern": [],
          "activities": 35
        },
        {
          "sectionIndex": 4,
          "unitIndex": 4,
          "title": "Menceritakan perjalanan yang menantang",
          "activityPattern": [],
          "activities": 36
        },
        {
          "sectionIndex": 4,
          "unitIndex": 4,
          "title": "Menghubungi layanan darurat",
          "activityPattern": [],
          "activities": 37
        },
        {
          "sectionIndex": 4,
          "unitIndex": 4,
          "title": "Membahas perayaan Tahun Baru lalu",
          "activityPattern": [],
          "activities": 38
        },
        {
          "sectionIndex": 4,
          "unitIndex": 4,
          "title": "Mendiskusikan kontribusi proyek",
          "activityPattern": [],
          "activities": 39
        },
        {
          "sectionIndex": 4,
          "unitIndex": 4,
          "title": "Mencari pemilik barang-barang",
          "activityPattern": [],
          "activities": 40
        },
        {
          "sectionIndex": 4,
          "unitIndex": 4,
          "title": "Memesan makanan di restoran",
          "activityPattern": [],
          "activities": 41
        },
        {
          "sectionIndex": 4,
          "unitIndex": 4,
          "title": "Membahas prestasi anak genius",
          "activityPattern": [],
          "activities": 42
        },
        {
          "sectionIndex": 4,
          "unitIndex": 4,
          "title": "Mendiskusikan tinggal di tempat lain",
          "activityPattern": [],
          "activities": 43
        },
        {
          "sectionIndex": 4,
          "unitIndex": 4,
          "title": "Memberi alasan ke teman sekelas",
          "activityPattern": [],
          "activities": 44
        },
        {
          "sectionIndex": 4,
          "unitIndex": 4,
          "title": "Menanyakan lokasi acara",
          "activityPattern": [],
          "activities": 45
        },
        {
          "sectionIndex": 4,
          "unitIndex": 4,
          "title": "Membahas isu politik lokal",
          "activityPattern": [],
          "activities": 46
        },
        {
          "sectionIndex": 4,
          "unitIndex": 4,
          "title": "Mengembalikan barang di toko",
          "activityPattern": [],
          "activities": 47
        },
        {
          "sectionIndex": 4,
          "unitIndex": 4,
          "title": "Mendeskripsikan potongan rambut",
          "activityPattern": [],
          "activities": 48
        },
        {
          "sectionIndex": 4,
          "unitIndex": 4,
          "title": "Menjelaskan tindakan ke polisi",
          "activityPattern": [],
          "activities": 49
        },
        {
          "sectionIndex": 4,
          "unitIndex": 4,
          "title": "Menjelaskan tentang perawatan hewan",
          "activityPattern": [],
          "activities": 50
        },
        {
          "sectionIndex": 4,
          "unitIndex": 4,
          "title": "Membahas berita terkini",
          "activityPattern": [],
          "activities": 51
        },
        {
          "sectionIndex": 4,
          "unitIndex": 4,
          "title": "Menampilkan prestasi dalam lamaran kerja",
          "activityPattern": [],
          "activities": 52
        },
        {
          "sectionIndex": 4,
          "unitIndex": 4,
          "title": "Membahas konteks sejarah seni",
          "activityPattern": [],
          "activities": 53
        },
        {
          "sectionIndex": 4,
          "unitIndex": 4,
          "title": "Membahas kebiasaan makan sehat",
          "activityPattern": [],
          "activities": 54
        },
        {
          "sectionIndex": 4,
          "unitIndex": 4,
          "title": "Membahas dongeng",
          "activityPattern": [],
          "activities": 55
        },
        {
          "sectionIndex": 4,
          "unitIndex": 4,
          "title": "Membuat janji temu dengan dokter",
          "activityPattern": [],
          "activities": 56
        },
        {
          "sectionIndex": 4,
          "unitIndex": 4,
          "title": "Mendeskripsikan perayaan tradisional",
          "activityPattern": [],
          "activities": 57
        },
        {
          "sectionIndex": 4,
          "unitIndex": 4,
          "title": "Menekankan pendapat dan tanggung jawab",
          "activityPattern": [],
          "activities": 58
        },
        {
          "sectionIndex": 4,
          "unitIndex": 4,
          "title": "Bergosip bersama teman",
          "activityPattern": [],
          "activities": 59
        },
        {
          "sectionIndex": 4,
          "unitIndex": 4,
          "title": "Mendeskripsikan tempat kejadian perkara",
          "activityPattern": [
            2025,
            12,
            5
          ],
          "activities": 2042
        }
      ]
    }
  ]
}