{
  "meta": {
    "key": "ptfru131",
    "courseTitle": "Russian → Portuguese",
    "scrapedAt": "2026-01-26T02:42:01.712Z",
    "sourceHash": "sha256:2a329df903221512",
    "fromLang": "Russian",
    "toLang": "Portuguese",
    "fromCode": "ru",
    "toCode": "pt",
    "level": "CEFR INTRO",
    "levelShort": "INTRO",
    "detailHref": "https://duolingodata.com/dat/ptfru131.html",
    "detailHrefHash": "sha256:3548cc47190626fb",
    "scrapeWarnings": [],
    "schemaVersion": "1.0.0"
  },
  "totals": {
    "sections": 4,
    "activities": 4806,
    "units": 131
  },
  "sections": [
    {
      "sectionIndex": 1,
      "unitCount": 11,
      "title": "CEFR Intro:",
      "rawTitle": "CEFR Intro:",
      "cefr": "INTRO:",
      "units": [
        {
          "sectionIndex": 1,
          "unitIndex": 1,
          "title": "Заказывайте в кафе",
          "activityPattern": [],
          "activities": 1
        },
        {
          "sectionIndex": 1,
          "unitIndex": 1,
          "title": "Приветствуйте и прощайтесь",
          "activityPattern": [],
          "activities": 2
        },
        {
          "sectionIndex": 1,
          "unitIndex": 1,
          "title": "Расскажите, откуда вы родом",
          "activityPattern": [],
          "activities": 3
        },
        {
          "sectionIndex": 1,
          "unitIndex": 1,
          "title": "Узнавайте членов семьи",
          "activityPattern": [],
          "activities": 4
        },
        {
          "sectionIndex": 1,
          "unitIndex": 1,
          "title": "Описывайте черты характера",
          "activityPattern": [],
          "activities": 5
        },
        {
          "sectionIndex": 1,
          "unitIndex": 1,
          "title": "Найдите свои вещи",
          "activityPattern": [],
          "activities": 6
        },
        {
          "sectionIndex": 1,
          "unitIndex": 1,
          "title": "Найдите места в городе",
          "activityPattern": [],
          "activities": 7
        },
        {
          "sectionIndex": 1,
          "unitIndex": 1,
          "title": "Используйте настоящее время",
          "activityPattern": [],
          "activities": 8
        },
        {
          "sectionIndex": 1,
          "unitIndex": 1,
          "title": "Обсуждайте погоду",
          "activityPattern": [],
          "activities": 9
        },
        {
          "sectionIndex": 1,
          "unitIndex": 1,
          "title": "Покупайте продукты",
          "activityPattern": [],
          "activities": 10
        },
        {
          "sectionIndex": 1,
          "unitIndex": 1,
          "title": "Опишите свой дом",
          "activityPattern": [],
          "activities": 11
        }
      ]
    },
    {
      "sectionIndex": 2,
      "unitCount": 30,
      "title": ":",
      "rawTitle": "CEFR A1:",
      "cefr": "A1",
      "units": [
        {
          "sectionIndex": 2,
          "unitIndex": 2,
          "title": "Используйте настоящее время",
          "activityPattern": [],
          "activities": 1
        },
        {
          "sectionIndex": 2,
          "unitIndex": 2,
          "title": "Обсуждайте спортивные занятия",
          "activityPattern": [],
          "activities": 2
        },
        {
          "sectionIndex": 2,
          "unitIndex": 2,
          "title": "Обсуждайте хобби",
          "activityPattern": [],
          "activities": 3
        },
        {
          "sectionIndex": 2,
          "unitIndex": 2,
          "title": "Участвуйте в классе",
          "activityPattern": [],
          "activities": 4
        },
        {
          "sectionIndex": 2,
          "unitIndex": 2,
          "title": "Заказывайте еду и напитки",
          "activityPattern": [],
          "activities": 5
        },
        {
          "sectionIndex": 2,
          "unitIndex": 2,
          "title": "Оценивайте еду и обслуживание",
          "activityPattern": [],
          "activities": 6
        },
        {
          "sectionIndex": 2,
          "unitIndex": 2,
          "title": "Найдите дорогу в городе",
          "activityPattern": [],
          "activities": 7
        },
        {
          "sectionIndex": 2,
          "unitIndex": 2,
          "title": "Используйте согласование по роду и числу",
          "activityPattern": [],
          "activities": 8
        },
        {
          "sectionIndex": 2,
          "unitIndex": 2,
          "title": "Обсудите ваше рабочее место",
          "activityPattern": [],
          "activities": 9
        },
        {
          "sectionIndex": 2,
          "unitIndex": 2,
          "title": "Покупайте продукты",
          "activityPattern": [],
          "activities": 10
        },
        {
          "sectionIndex": 2,
          "unitIndex": 2,
          "title": "Притяжательные прилагательные",
          "activityPattern": [],
          "activities": 11
        },
        {
          "sectionIndex": 2,
          "unitIndex": 2,
          "title": "Определите предметы в классе",
          "activityPattern": [],
          "activities": 12
        },
        {
          "sectionIndex": 2,
          "unitIndex": 2,
          "title": "Спросите о чувствах",
          "activityPattern": [],
          "activities": 13
        },
        {
          "sectionIndex": 2,
          "unitIndex": 2,
          "title": "Узнайте дорогу",
          "activityPattern": [],
          "activities": 14
        },
        {
          "sectionIndex": 2,
          "unitIndex": 2,
          "title": "Используйте квантификаторы в вопросах",
          "activityPattern": [],
          "activities": 15
        },
        {
          "sectionIndex": 2,
          "unitIndex": 2,
          "title": "Знакомьтесь с новыми людьми",
          "activityPattern": [],
          "activities": 16
        },
        {
          "sectionIndex": 2,
          "unitIndex": 2,
          "title": "Опишите членов семьи",
          "activityPattern": [],
          "activities": 17
        },
        {
          "sectionIndex": 2,
          "unitIndex": 2,
          "title": "Планируйте свое расписание",
          "activityPattern": [],
          "activities": 18
        },
        {
          "sectionIndex": 2,
          "unitIndex": 2,
          "title": "Используйте формальные обращения",
          "activityPattern": [],
          "activities": 19
        },
        {
          "sectionIndex": 2,
          "unitIndex": 2,
          "title": "Делитесь личными историями",
          "activityPattern": [],
          "activities": 20
        },
        {
          "sectionIndex": 2,
          "unitIndex": 2,
          "title": "Используйте настоящее время",
          "activityPattern": [],
          "activities": 21
        },
        {
          "sectionIndex": 2,
          "unitIndex": 2,
          "title": "Обсудите животных и их среду обитания",
          "activityPattern": [],
          "activities": 22
        },
        {
          "sectionIndex": 2,
          "unitIndex": 2,
          "title": "Описывайте повседневные дела",
          "activityPattern": [],
          "activities": 23
        },
        {
          "sectionIndex": 2,
          "unitIndex": 2,
          "title": "Используйте возвратные глаголы",
          "activityPattern": [],
          "activities": 24
        },
        {
          "sectionIndex": 2,
          "unitIndex": 2,
          "title": "Обсудите свои хобби",
          "activityPattern": [],
          "activities": 25
        },
        {
          "sectionIndex": 2,
          "unitIndex": 2,
          "title": "Обсуждайте музыкальные события",
          "activityPattern": [],
          "activities": 26
        },
        {
          "sectionIndex": 2,
          "unitIndex": 2,
          "title": "Обсудите досуг и развлечения",
          "activityPattern": [],
          "activities": 27
        },
        {
          "sectionIndex": 2,
          "unitIndex": 2,
          "title": "Обратитесь за медицинской помощью",
          "activityPattern": [],
          "activities": 28
        },
        {
          "sectionIndex": 2,
          "unitIndex": 2,
          "title": "Обсудите свой путь на работу",
          "activityPattern": [],
          "activities": 29
        },
        {
          "sectionIndex": 2,
          "unitIndex": 2,
          "title": "Обсудите дни рождения",
          "activityPattern": [],
          "activities": 30
        }
      ]
    },
    {
      "sectionIndex": 3,
      "unitCount": 30,
      "title": ":",
      "rawTitle": "CEFR A1:",
      "cefr": "A1",
      "units": [
        {
          "sectionIndex": 3,
          "unitIndex": 3,
          "title": "Выражайте предпочтения и желания",
          "activityPattern": [],
          "activities": 1
        },
        {
          "sectionIndex": 3,
          "unitIndex": 3,
          "title": "Поговорите о выходе в свет",
          "activityPattern": [],
          "activities": 2
        },
        {
          "sectionIndex": 3,
          "unitIndex": 3,
          "title": "Планируйте оздоровительные занятия",
          "activityPattern": [],
          "activities": 3
        },
        {
          "sectionIndex": 3,
          "unitIndex": 3,
          "title": "Выражайте нужды и желания",
          "activityPattern": [],
          "activities": 4
        },
        {
          "sectionIndex": 3,
          "unitIndex": 3,
          "title": "Планируйте поездку",
          "activityPattern": [],
          "activities": 5
        },
        {
          "sectionIndex": 3,
          "unitIndex": 3,
          "title": "Выразите предстоящие действия",
          "activityPattern": [],
          "activities": 6
        },
        {
          "sectionIndex": 3,
          "unitIndex": 3,
          "title": "Исследуйте город",
          "activityPattern": [],
          "activities": 7
        },
        {
          "sectionIndex": 3,
          "unitIndex": 3,
          "title": "Используйте указательные слова",
          "activityPattern": [],
          "activities": 8
        },
        {
          "sectionIndex": 3,
          "unitIndex": 3,
          "title": "Найдите продукты питания",
          "activityPattern": [],
          "activities": 9
        },
        {
          "sectionIndex": 3,
          "unitIndex": 3,
          "title": "Празднуйте с друзьями",
          "activityPattern": [],
          "activities": 10
        },
        {
          "sectionIndex": 3,
          "unitIndex": 3,
          "title": "Покупайте одежду",
          "activityPattern": [],
          "activities": 11
        },
        {
          "sectionIndex": 3,
          "unitIndex": 3,
          "title": "Используйте настоящее время для рутины",
          "activityPattern": [],
          "activities": 12
        },
        {
          "sectionIndex": 3,
          "unitIndex": 3,
          "title": "Обсудите проблемы со здоровьем",
          "activityPattern": [],
          "activities": 13
        },
        {
          "sectionIndex": 3,
          "unitIndex": 3,
          "title": "Неопределенные местоимения и прилаг-е",
          "activityPattern": [],
          "activities": 14
        },
        {
          "sectionIndex": 3,
          "unitIndex": 3,
          "title": "Решайте рабочие проблемы",
          "activityPattern": [],
          "activities": 15
        },
        {
          "sectionIndex": 3,
          "unitIndex": 3,
          "title": "Используйте указательные слова",
          "activityPattern": [],
          "activities": 16
        },
        {
          "sectionIndex": 3,
          "unitIndex": 3,
          "title": "Обсуждайте фильмы",
          "activityPattern": [],
          "activities": 17
        },
        {
          "sectionIndex": 3,
          "unitIndex": 3,
          "title": "Участвуйте в мероприятиях",
          "activityPattern": [],
          "activities": 18
        },
        {
          "sectionIndex": 3,
          "unitIndex": 3,
          "title": "Отправляйте и получайте почту",
          "activityPattern": [],
          "activities": 19
        },
        {
          "sectionIndex": 3,
          "unitIndex": 3,
          "title": "Используйте настоящее продолженное время",
          "activityPattern": [],
          "activities": 20
        },
        {
          "sectionIndex": 3,
          "unitIndex": 3,
          "title": "Обсуждайте погоду",
          "activityPattern": [],
          "activities": 21
        },
        {
          "sectionIndex": 3,
          "unitIndex": 3,
          "title": "Обсудите рабочий стресс",
          "activityPattern": [],
          "activities": 22
        },
        {
          "sectionIndex": 3,
          "unitIndex": 3,
          "title": "Используйте наречия",
          "activityPattern": [],
          "activities": 23
        },
        {
          "sectionIndex": 3,
          "unitIndex": 3,
          "title": "Используйте квантификаторы",
          "activityPattern": [],
          "activities": 24
        },
        {
          "sectionIndex": 3,
          "unitIndex": 3,
          "title": "Общайтесь онлайн",
          "activityPattern": [],
          "activities": 25
        },
        {
          "sectionIndex": 3,
          "unitIndex": 3,
          "title": "Играйте в спорт и игры",
          "activityPattern": [],
          "activities": 26
        },
        {
          "sectionIndex": 3,
          "unitIndex": 3,
          "title": "Выполняйте домашние дела",
          "activityPattern": [],
          "activities": 27
        },
        {
          "sectionIndex": 3,
          "unitIndex": 3,
          "title": "Действуйте в экстренных ситуациях",
          "activityPattern": [],
          "activities": 28
        },
        {
          "sectionIndex": 3,
          "unitIndex": 3,
          "title": "Модальные глаголы для нужд и разрешений",
          "activityPattern": [],
          "activities": 29
        },
        {
          "sectionIndex": 3,
          "unitIndex": 3,
          "title": "Работайте в офисе",
          "activityPattern": [],
          "activities": 30
        }
      ]
    },
    {
      "sectionIndex": 4,
      "unitCount": 60,
      "title": ":",
      "rawTitle": "CEFR A2:",
      "cefr": "A2",
      "units": [
        {
          "sectionIndex": 4,
          "unitIndex": 4,
          "title": "Обсудите планы на завтра",
          "activityPattern": [],
          "activities": 1
        },
        {
          "sectionIndex": 4,
          "unitIndex": 4,
          "title": "Вежливо объясните технические проблемы",
          "activityPattern": [],
          "activities": 2
        },
        {
          "sectionIndex": 4,
          "unitIndex": 4,
          "title": "Обсудите наблюдения о городе",
          "activityPattern": [],
          "activities": 3
        },
        {
          "sectionIndex": 4,
          "unitIndex": 4,
          "title": "Обсудите предпочтения в кино",
          "activityPattern": [],
          "activities": 4
        },
        {
          "sectionIndex": 4,
          "unitIndex": 4,
          "title": "Описывайте членов семьи",
          "activityPattern": [],
          "activities": 5
        },
        {
          "sectionIndex": 4,
          "unitIndex": 4,
          "title": "Описывайте знаменитостей",
          "activityPattern": [],
          "activities": 6
        },
        {
          "sectionIndex": 4,
          "unitIndex": 4,
          "title": "Обсудите опоздания на встречи",
          "activityPattern": [],
          "activities": 7
        },
        {
          "sectionIndex": 4,
          "unitIndex": 4,
          "title": "Обсудите неудачи на свадьбе",
          "activityPattern": [],
          "activities": 8
        },
        {
          "sectionIndex": 4,
          "unitIndex": 4,
          "title": "Опишите задачи волонтеров и их порядок",
          "activityPattern": [],
          "activities": 9
        },
        {
          "sectionIndex": 4,
          "unitIndex": 4,
          "title": "Спрашивайте о пропавших вещах",
          "activityPattern": [],
          "activities": 10
        },
        {
          "sectionIndex": 4,
          "unitIndex": 4,
          "title": "Покупайте овощи на рынке",
          "activityPattern": [],
          "activities": 11
        },
        {
          "sectionIndex": 4,
          "unitIndex": 4,
          "title": "Обменивайтесь подарками с семьей",
          "activityPattern": [],
          "activities": 12
        },
        {
          "sectionIndex": 4,
          "unitIndex": 4,
          "title": "Спрашивайте о кулинарных ингредиентах",
          "activityPattern": [],
          "activities": 13
        },
        {
          "sectionIndex": 4,
          "unitIndex": 4,
          "title": "Обсудите свадебное мероприятие",
          "activityPattern": [],
          "activities": 14
        },
        {
          "sectionIndex": 4,
          "unitIndex": 4,
          "title": "Обсудите аренду дома",
          "activityPattern": [],
          "activities": 15
        },
        {
          "sectionIndex": 4,
          "unitIndex": 4,
          "title": "Вежливо запросите информацию о проекте",
          "activityPattern": [],
          "activities": 16
        },
        {
          "sectionIndex": 4,
          "unitIndex": 4,
          "title": "Опишите опыт свидания",
          "activityPattern": [],
          "activities": 17
        },
        {
          "sectionIndex": 4,
          "unitIndex": 4,
          "title": "Вежливо узнавайте дорогу",
          "activityPattern": [],
          "activities": 18
        },
        {
          "sectionIndex": 4,
          "unitIndex": 4,
          "title": "Обсудите восстановление с врачом",
          "activityPattern": [],
          "activities": 19
        },
        {
          "sectionIndex": 4,
          "unitIndex": 4,
          "title": "Общайтесь с командой",
          "activityPattern": [],
          "activities": 20
        },
        {
          "sectionIndex": 4,
          "unitIndex": 4,
          "title": "Давайте указания по домашним делам",
          "activityPattern": [],
          "activities": 21
        },
        {
          "sectionIndex": 4,
          "unitIndex": 4,
          "title": "Делитесь семейными историями",
          "activityPattern": [],
          "activities": 22
        },
        {
          "sectionIndex": 4,
          "unitIndex": 4,
          "title": "Обсудите детские воспоминания о покупках",
          "activityPattern": [],
          "activities": 23
        },
        {
          "sectionIndex": 4,
          "unitIndex": 4,
          "title": "Делитесь опытом из прошлого",
          "activityPattern": [],
          "activities": 24
        },
        {
          "sectionIndex": 4,
          "unitIndex": 4,
          "title": "Арендуйте или покупайте дом",
          "activityPattern": [],
          "activities": 25
        },
        {
          "sectionIndex": 4,
          "unitIndex": 4,
          "title": "Планируйте тур в природные парки",
          "activityPattern": [],
          "activities": 26
        },
        {
          "sectionIndex": 4,
          "unitIndex": 4,
          "title": "Обсудите прошлый опыт",
          "activityPattern": [],
          "activities": 27
        },
        {
          "sectionIndex": 4,
          "unitIndex": 4,
          "title": "Обсудите свою историю жизни",
          "activityPattern": [],
          "activities": 28
        },
        {
          "sectionIndex": 4,
          "unitIndex": 4,
          "title": "Обсудите опыт работы",
          "activityPattern": [],
          "activities": 29
        },
        {
          "sectionIndex": 4,
          "unitIndex": 4,
          "title": "Напишите друзьям на португальском",
          "activityPattern": [],
          "activities": 30
        },
        {
          "sectionIndex": 4,
          "unitIndex": 4,
          "title": "Делитесь мнениями о трендах в здоровье",
          "activityPattern": [],
          "activities": 31
        },
        {
          "sectionIndex": 4,
          "unitIndex": 4,
          "title": "Говорите о прошлых привычках",
          "activityPattern": [],
          "activities": 32
        },
        {
          "sectionIndex": 4,
          "unitIndex": 4,
          "title": "Обсудите прошлые и недавние события",
          "activityPattern": [],
          "activities": 33
        },
        {
          "sectionIndex": 4,
          "unitIndex": 4,
          "title": "Отмейчайте достижения на церемониях",
          "activityPattern": [],
          "activities": 34
        },
        {
          "sectionIndex": 4,
          "unitIndex": 4,
          "title": "Описывайте мебель на португальском",
          "activityPattern": [],
          "activities": 35
        },
        {
          "sectionIndex": 4,
          "unitIndex": 4,
          "title": "Опишите трудную поездку",
          "activityPattern": [],
          "activities": 36
        },
        {
          "sectionIndex": 4,
          "unitIndex": 4,
          "title": "Звоните в службы спасения",
          "activityPattern": [],
          "activities": 37
        },
        {
          "sectionIndex": 4,
          "unitIndex": 4,
          "title": "Обсудите прошедшие новогодние праздники",
          "activityPattern": [],
          "activities": 38
        },
        {
          "sectionIndex": 4,
          "unitIndex": 4,
          "title": "Обсудите вклад в проект",
          "activityPattern": [],
          "activities": 39
        },
        {
          "sectionIndex": 4,
          "unitIndex": 4,
          "title": "Найдите владельцев вещей",
          "activityPattern": [],
          "activities": 40
        },
        {
          "sectionIndex": 4,
          "unitIndex": 4,
          "title": "Заказывайте еду в ресторане",
          "activityPattern": [],
          "activities": 41
        },
        {
          "sectionIndex": 4,
          "unitIndex": 4,
          "title": "Обсудите достижения вундеркиндов",
          "activityPattern": [],
          "activities": 42
        },
        {
          "sectionIndex": 4,
          "unitIndex": 4,
          "title": "Обсудите жизнь в разных местах",
          "activityPattern": [],
          "activities": 43
        },
        {
          "sectionIndex": 4,
          "unitIndex": 4,
          "title": "Оправдывайтесь перед одноклассниками",
          "activityPattern": [],
          "activities": 44
        },
        {
          "sectionIndex": 4,
          "unitIndex": 4,
          "title": "Узнавайте место проведения события",
          "activityPattern": [],
          "activities": 45
        },
        {
          "sectionIndex": 4,
          "unitIndex": 4,
          "title": "Обсудите местные политические вопросы",
          "activityPattern": [],
          "activities": 46
        },
        {
          "sectionIndex": 4,
          "unitIndex": 4,
          "title": "Возвращайте вещи в магазин",
          "activityPattern": [],
          "activities": 47
        },
        {
          "sectionIndex": 4,
          "unitIndex": 4,
          "title": "Опишите желаемую стрижку",
          "activityPattern": [],
          "activities": 48
        },
        {
          "sectionIndex": 4,
          "unitIndex": 4,
          "title": "Объясняйте действия полиции",
          "activityPattern": [],
          "activities": 49
        },
        {
          "sectionIndex": 4,
          "unitIndex": 4,
          "title": "Описывайте ежедневный уход за питомцем",
          "activityPattern": [],
          "activities": 50
        },
        {
          "sectionIndex": 4,
          "unitIndex": 4,
          "title": "Обсудите текущие события",
          "activityPattern": [],
          "activities": 51
        },
        {
          "sectionIndex": 4,
          "unitIndex": 4,
          "title": "Подчеркивайте достижения в заявках",
          "activityPattern": [],
          "activities": 52
        },
        {
          "sectionIndex": 4,
          "unitIndex": 4,
          "title": "Обсудите контекст истории искусства",
          "activityPattern": [],
          "activities": 53
        },
        {
          "sectionIndex": 4,
          "unitIndex": 4,
          "title": "Обсудите здоровые привычки питания",
          "activityPattern": [],
          "activities": 54
        },
        {
          "sectionIndex": 4,
          "unitIndex": 4,
          "title": "Обсудите сказку",
          "activityPattern": [],
          "activities": 55
        },
        {
          "sectionIndex": 4,
          "unitIndex": 4,
          "title": "Записывайтесь к врачу",
          "activityPattern": [],
          "activities": 56
        },
        {
          "sectionIndex": 4,
          "unitIndex": 4,
          "title": "Опишите традиционные праздничные обычаи",
          "activityPattern": [],
          "activities": 57
        },
        {
          "sectionIndex": 4,
          "unitIndex": 4,
          "title": "Подчеркивайте мнения и обязанности",
          "activityPattern": [],
          "activities": 58
        },
        {
          "sectionIndex": 4,
          "unitIndex": 4,
          "title": "Сплетничайте с друзьями",
          "activityPattern": [],
          "activities": 59
        },
        {
          "sectionIndex": 4,
          "unitIndex": 4,
          "title": "Опишите место преступления",
          "activityPattern": [
            2025,
            12,
            3
          ],
          "activities": 2040
        }
      ]
    }
  ]
}