{
  "meta": {
    "key": "zhfen130",
    "courseTitle": "English → Chinese",
    "scrapedAt": "2026-01-26T02:42:01.712Z",
    "sourceHash": "sha256:9a5f924e3bfbd6f5",
    "fromLang": "English",
    "toLang": "Chinese",
    "fromCode": "en",
    "toCode": "zh",
    "level": "CEFR INTRO",
    "levelShort": "INTRO",
    "detailHref": "https://duolingodata.com/dat/zhfen130.html",
    "detailHrefHash": "sha256:28d0f5471d416e76",
    "scrapeWarnings": [],
    "schemaVersion": "1.0.0"
  },
  "totals": {
    "sections": 4,
    "activities": 4804,
    "units": 130
  },
  "sections": [
    {
      "sectionIndex": 1,
      "unitCount": 10,
      "title": "CEFR Intro:",
      "rawTitle": "CEFR Intro:",
      "cefr": "INTRO:",
      "units": [
        {
          "sectionIndex": 1,
          "unitIndex": 1,
          "title": "Name food and drinks",
          "activityPattern": [],
          "activities": 1
        },
        {
          "sectionIndex": 1,
          "unitIndex": 1,
          "title": "Talk about nationalities",
          "activityPattern": [],
          "activities": 2
        },
        {
          "sectionIndex": 1,
          "unitIndex": 1,
          "title": "Discuss professions",
          "activityPattern": [],
          "activities": 3
        },
        {
          "sectionIndex": 1,
          "unitIndex": 1,
          "title": "Discuss your courses",
          "activityPattern": [],
          "activities": 4
        },
        {
          "sectionIndex": 1,
          "unitIndex": 1,
          "title": "Use possessive pronouns",
          "activityPattern": [],
          "activities": 5
        },
        {
          "sectionIndex": 1,
          "unitIndex": 1,
          "title": "Talk about places you visit",
          "activityPattern": [],
          "activities": 6
        },
        {
          "sectionIndex": 1,
          "unitIndex": 1,
          "title": "Order drinks",
          "activityPattern": [],
          "activities": 7
        },
        {
          "sectionIndex": 1,
          "unitIndex": 1,
          "title": "Locate travel essentials",
          "activityPattern": [],
          "activities": 8
        },
        {
          "sectionIndex": 1,
          "unitIndex": 1,
          "title": "Introduce yourself and your classes",
          "activityPattern": [],
          "activities": 9
        },
        {
          "sectionIndex": 1,
          "unitIndex": 1,
          "title": "Discuss sports preferences",
          "activityPattern": [],
          "activities": 10
        }
      ]
    },
    {
      "sectionIndex": 2,
      "unitCount": 30,
      "title": ":",
      "rawTitle": "CEFR A1:",
      "cefr": "A1",
      "units": [
        {
          "sectionIndex": 2,
          "unitIndex": 2,
          "title": "Use adjectives for description",
          "activityPattern": [],
          "activities": 1
        },
        {
          "sectionIndex": 2,
          "unitIndex": 2,
          "title": "Explore Beijing",
          "activityPattern": [],
          "activities": 2
        },
        {
          "sectionIndex": 2,
          "unitIndex": 2,
          "title": "Use suggestion particles",
          "activityPattern": [],
          "activities": 3
        },
        {
          "sectionIndex": 2,
          "unitIndex": 2,
          "title": "Use commands",
          "activityPattern": [],
          "activities": 4
        },
        {
          "sectionIndex": 2,
          "unitIndex": 2,
          "title": "Use modal verbs to express ability",
          "activityPattern": [],
          "activities": 5
        },
        {
          "sectionIndex": 2,
          "unitIndex": 2,
          "title": "Ask for permission",
          "activityPattern": [],
          "activities": 6
        },
        {
          "sectionIndex": 2,
          "unitIndex": 2,
          "title": "Clean and organize your home",
          "activityPattern": [],
          "activities": 7
        },
        {
          "sectionIndex": 2,
          "unitIndex": 2,
          "title": "Use the present progressive",
          "activityPattern": [],
          "activities": 8
        },
        {
          "sectionIndex": 2,
          "unitIndex": 2,
          "title": "Seek medical help",
          "activityPattern": [],
          "activities": 9
        },
        {
          "sectionIndex": 2,
          "unitIndex": 2,
          "title": "Plan a birthday party",
          "activityPattern": [],
          "activities": 10
        },
        {
          "sectionIndex": 2,
          "unitIndex": 2,
          "title": "Ask for directions on campus",
          "activityPattern": [],
          "activities": 11
        },
        {
          "sectionIndex": 2,
          "unitIndex": 2,
          "title": "Use comparatives",
          "activityPattern": [],
          "activities": 12
        },
        {
          "sectionIndex": 2,
          "unitIndex": 2,
          "title": "Talk about your childhood",
          "activityPattern": [],
          "activities": 13
        },
        {
          "sectionIndex": 2,
          "unitIndex": 2,
          "title": "Plan your activities",
          "activityPattern": [],
          "activities": 14
        },
        {
          "sectionIndex": 2,
          "unitIndex": 2,
          "title": "Use time expressions",
          "activityPattern": [],
          "activities": 15
        },
        {
          "sectionIndex": 2,
          "unitIndex": 2,
          "title": "Shop for clothes",
          "activityPattern": [],
          "activities": 16
        },
        {
          "sectionIndex": 2,
          "unitIndex": 2,
          "title": "Attend a concert",
          "activityPattern": [],
          "activities": 17
        },
        {
          "sectionIndex": 2,
          "unitIndex": 2,
          "title": "Ask questions",
          "activityPattern": [],
          "activities": 18
        },
        {
          "sectionIndex": 2,
          "unitIndex": 2,
          "title": "Expressing possession",
          "activityPattern": [],
          "activities": 19
        },
        {
          "sectionIndex": 2,
          "unitIndex": 2,
          "title": "Express feelings",
          "activityPattern": [],
          "activities": 20
        },
        {
          "sectionIndex": 2,
          "unitIndex": 2,
          "title": "Talk about the weather",
          "activityPattern": [],
          "activities": 21
        },
        {
          "sectionIndex": 2,
          "unitIndex": 2,
          "title": "Talk about friends",
          "activityPattern": [],
          "activities": 22
        },
        {
          "sectionIndex": 2,
          "unitIndex": 2,
          "title": "Describe your daily routine",
          "activityPattern": [],
          "activities": 23
        },
        {
          "sectionIndex": 2,
          "unitIndex": 2,
          "title": "Manage daily tasks",
          "activityPattern": [],
          "activities": 24
        },
        {
          "sectionIndex": 2,
          "unitIndex": 2,
          "title": "Shop online",
          "activityPattern": [],
          "activities": 25
        },
        {
          "sectionIndex": 2,
          "unitIndex": 2,
          "title": "Discuss rental details",
          "activityPattern": [],
          "activities": 26
        },
        {
          "sectionIndex": 2,
          "unitIndex": 2,
          "title": "Use indirect objects",
          "activityPattern": [],
          "activities": 27
        },
        {
          "sectionIndex": 2,
          "unitIndex": 2,
          "title": "Ask for directions",
          "activityPattern": [],
          "activities": 28
        },
        {
          "sectionIndex": 2,
          "unitIndex": 2,
          "title": "Discuss sports excitement",
          "activityPattern": [],
          "activities": 29
        },
        {
          "sectionIndex": 2,
          "unitIndex": 2,
          "title": "Handle an emergency",
          "activityPattern": [],
          "activities": 30
        }
      ]
    },
    {
      "sectionIndex": 3,
      "unitCount": 30,
      "title": ":",
      "rawTitle": "CEFR A1:",
      "cefr": "A1",
      "units": [
        {
          "sectionIndex": 3,
          "unitIndex": 3,
          "title": "Navigate the city",
          "activityPattern": [],
          "activities": 1
        },
        {
          "sectionIndex": 3,
          "unitIndex": 3,
          "title": "Shop for health products",
          "activityPattern": [],
          "activities": 2
        },
        {
          "sectionIndex": 3,
          "unitIndex": 3,
          "title": "Attend a graduation",
          "activityPattern": [],
          "activities": 3
        },
        {
          "sectionIndex": 3,
          "unitIndex": 3,
          "title": "Report a problem",
          "activityPattern": [],
          "activities": 4
        },
        {
          "sectionIndex": 3,
          "unitIndex": 3,
          "title": "Explore studying abroad",
          "activityPattern": [],
          "activities": 5
        },
        {
          "sectionIndex": 3,
          "unitIndex": 3,
          "title": "Discuss movies",
          "activityPattern": [],
          "activities": 6
        },
        {
          "sectionIndex": 3,
          "unitIndex": 3,
          "title": "Use time expressions for events",
          "activityPattern": [],
          "activities": 7
        },
        {
          "sectionIndex": 3,
          "unitIndex": 3,
          "title": "Ask for clarification",
          "activityPattern": [],
          "activities": 8
        },
        {
          "sectionIndex": 3,
          "unitIndex": 3,
          "title": "Meet new people",
          "activityPattern": [],
          "activities": 9
        },
        {
          "sectionIndex": 3,
          "unitIndex": 3,
          "title": "Join activities",
          "activityPattern": [],
          "activities": 10
        },
        {
          "sectionIndex": 3,
          "unitIndex": 3,
          "title": "Form yes/no questions",
          "activityPattern": [],
          "activities": 11
        },
        {
          "sectionIndex": 3,
          "unitIndex": 3,
          "title": "Use comparatives",
          "activityPattern": [],
          "activities": 12
        },
        {
          "sectionIndex": 3,
          "unitIndex": 3,
          "title": "Evaluate food and drinks",
          "activityPattern": [],
          "activities": 13
        },
        {
          "sectionIndex": 3,
          "unitIndex": 3,
          "title": "Shop for groceries",
          "activityPattern": [],
          "activities": 14
        },
        {
          "sectionIndex": 3,
          "unitIndex": 3,
          "title": "Cook with recipes",
          "activityPattern": [],
          "activities": 15
        },
        {
          "sectionIndex": 3,
          "unitIndex": 3,
          "title": "Enjoy a music festival",
          "activityPattern": [],
          "activities": 16
        },
        {
          "sectionIndex": 3,
          "unitIndex": 3,
          "title": "Catch up with friends",
          "activityPattern": [],
          "activities": 17
        },
        {
          "sectionIndex": 3,
          "unitIndex": 3,
          "title": "Form complex sentences with contrast",
          "activityPattern": [],
          "activities": 18
        },
        {
          "sectionIndex": 3,
          "unitIndex": 3,
          "title": "Arrange your home",
          "activityPattern": [],
          "activities": 19
        },
        {
          "sectionIndex": 3,
          "unitIndex": 3,
          "title": "Solve work problems",
          "activityPattern": [],
          "activities": 20
        },
        {
          "sectionIndex": 3,
          "unitIndex": 3,
          "title": "Emphasizing details in past events",
          "activityPattern": [],
          "activities": 21
        },
        {
          "sectionIndex": 3,
          "unitIndex": 3,
          "title": "Share your life story",
          "activityPattern": [],
          "activities": 22
        },
        {
          "sectionIndex": 3,
          "unitIndex": 3,
          "title": "Use directional phrases and questions",
          "activityPattern": [],
          "activities": 23
        },
        {
          "sectionIndex": 3,
          "unitIndex": 3,
          "title": "Discuss personal details",
          "activityPattern": [],
          "activities": 24
        },
        {
          "sectionIndex": 3,
          "unitIndex": 3,
          "title": "Discuss interests with neighbors",
          "activityPattern": [],
          "activities": 25
        },
        {
          "sectionIndex": 3,
          "unitIndex": 3,
          "title": "Form compound sentences",
          "activityPattern": [],
          "activities": 26
        },
        {
          "sectionIndex": 3,
          "unitIndex": 3,
          "title": "Navigate a mall",
          "activityPattern": [],
          "activities": 27
        },
        {
          "sectionIndex": 3,
          "unitIndex": 3,
          "title": "Handle an emergency",
          "activityPattern": [],
          "activities": 28
        },
        {
          "sectionIndex": 3,
          "unitIndex": 3,
          "title": "Make excuses",
          "activityPattern": [],
          "activities": 29
        },
        {
          "sectionIndex": 3,
          "unitIndex": 3,
          "title": "Run errands",
          "activityPattern": [],
          "activities": 30
        }
      ]
    },
    {
      "sectionIndex": 4,
      "unitCount": 60,
      "title": ":",
      "rawTitle": "CEFR A2:",
      "cefr": "A2",
      "units": [
        {
          "sectionIndex": 4,
          "unitIndex": 4,
          "title": "Share a busy week",
          "activityPattern": [],
          "activities": 1
        },
        {
          "sectionIndex": 4,
          "unitIndex": 4,
          "title": "Recall school memories",
          "activityPattern": [],
          "activities": 2
        },
        {
          "sectionIndex": 4,
          "unitIndex": 4,
          "title": "Describe a day unplugged",
          "activityPattern": [],
          "activities": 3
        },
        {
          "sectionIndex": 4,
          "unitIndex": 4,
          "title": "Comfort a stressed friend",
          "activityPattern": [],
          "activities": 4
        },
        {
          "sectionIndex": 4,
          "unitIndex": 4,
          "title": "Celebrate traditional Chinese festivals",
          "activityPattern": [],
          "activities": 5
        },
        {
          "sectionIndex": 4,
          "unitIndex": 4,
          "title": "Shop during festival sales",
          "activityPattern": [],
          "activities": 6
        },
        {
          "sectionIndex": 4,
          "unitIndex": 4,
          "title": "Describe a bad restaurant experience",
          "activityPattern": [],
          "activities": 7
        },
        {
          "sectionIndex": 4,
          "unitIndex": 4,
          "title": "Discuss client project details",
          "activityPattern": [],
          "activities": 8
        },
        {
          "sectionIndex": 4,
          "unitIndex": 4,
          "title": "Use kitchen vocabulary",
          "activityPattern": [],
          "activities": 9
        },
        {
          "sectionIndex": 4,
          "unitIndex": 4,
          "title": "Ask for exchange advice",
          "activityPattern": [],
          "activities": 10
        },
        {
          "sectionIndex": 4,
          "unitIndex": 4,
          "title": "Describe past travel accidents",
          "activityPattern": [],
          "activities": 11
        },
        {
          "sectionIndex": 4,
          "unitIndex": 4,
          "title": "Call home during trips",
          "activityPattern": [],
          "activities": 12
        },
        {
          "sectionIndex": 4,
          "unitIndex": 4,
          "title": "Solve an office mystery",
          "activityPattern": [],
          "activities": 13
        },
        {
          "sectionIndex": 4,
          "unitIndex": 4,
          "title": "Describe art pieces",
          "activityPattern": [],
          "activities": 14
        },
        {
          "sectionIndex": 4,
          "unitIndex": 4,
          "title": "Vlog about travel experiences",
          "activityPattern": [],
          "activities": 15
        },
        {
          "sectionIndex": 4,
          "unitIndex": 4,
          "title": "Make new year resolutions",
          "activityPattern": [],
          "activities": 16
        },
        {
          "sectionIndex": 4,
          "unitIndex": 4,
          "title": "Discuss team performance reviews",
          "activityPattern": [],
          "activities": 17
        },
        {
          "sectionIndex": 4,
          "unitIndex": 4,
          "title": "Compare art festival performances",
          "activityPattern": [],
          "activities": 18
        },
        {
          "sectionIndex": 4,
          "unitIndex": 4,
          "title": "Conduct research for school",
          "activityPattern": [],
          "activities": 19
        },
        {
          "sectionIndex": 4,
          "unitIndex": 4,
          "title": "Ask questions while traveling",
          "activityPattern": [],
          "activities": 20
        },
        {
          "sectionIndex": 4,
          "unitIndex": 4,
          "title": "Discuss people and events",
          "activityPattern": [],
          "activities": 21
        },
        {
          "sectionIndex": 4,
          "unitIndex": 4,
          "title": "Discuss proposing to someone",
          "activityPattern": [],
          "activities": 22
        },
        {
          "sectionIndex": 4,
          "unitIndex": 4,
          "title": "Call your parents",
          "activityPattern": [],
          "activities": 23
        },
        {
          "sectionIndex": 4,
          "unitIndex": 4,
          "title": "Plan a fun evening",
          "activityPattern": [],
          "activities": 24
        },
        {
          "sectionIndex": 4,
          "unitIndex": 4,
          "title": "Plan a trip together",
          "activityPattern": [],
          "activities": 25
        },
        {
          "sectionIndex": 4,
          "unitIndex": 4,
          "title": "Discuss healthy lifestyle choices",
          "activityPattern": [],
          "activities": 26
        },
        {
          "sectionIndex": 4,
          "unitIndex": 4,
          "title": "Host a housewarming party",
          "activityPattern": [],
          "activities": 27
        },
        {
          "sectionIndex": 4,
          "unitIndex": 4,
          "title": "Discuss family photo album",
          "activityPattern": [],
          "activities": 28
        },
        {
          "sectionIndex": 4,
          "unitIndex": 4,
          "title": "Discuss favorite celebrities",
          "activityPattern": [],
          "activities": 29
        },
        {
          "sectionIndex": 4,
          "unitIndex": 4,
          "title": "Discuss your child's report",
          "activityPattern": [],
          "activities": 30
        },
        {
          "sectionIndex": 4,
          "unitIndex": 4,
          "title": "Compare past and present countryside",
          "activityPattern": [],
          "activities": 31
        },
        {
          "sectionIndex": 4,
          "unitIndex": 4,
          "title": "Buy groceries at supermarket",
          "activityPattern": [],
          "activities": 32
        },
        {
          "sectionIndex": 4,
          "unitIndex": 4,
          "title": "Discuss favorite TV shows",
          "activityPattern": [],
          "activities": 33
        },
        {
          "sectionIndex": 4,
          "unitIndex": 4,
          "title": "Negotiate buying a house",
          "activityPattern": [],
          "activities": 34
        },
        {
          "sectionIndex": 4,
          "unitIndex": 4,
          "title": "Discuss feelings with friends",
          "activityPattern": [],
          "activities": 35
        },
        {
          "sectionIndex": 4,
          "unitIndex": 4,
          "title": "Discuss your weekly schedule",
          "activityPattern": [],
          "activities": 36
        },
        {
          "sectionIndex": 4,
          "unitIndex": 4,
          "title": "Explore cities in China",
          "activityPattern": [],
          "activities": 37
        },
        {
          "sectionIndex": 4,
          "unitIndex": 4,
          "title": "Describe symptoms to a doctor",
          "activityPattern": [],
          "activities": 38
        },
        {
          "sectionIndex": 4,
          "unitIndex": 4,
          "title": "Reconnect with old friends",
          "activityPattern": [],
          "activities": 39
        },
        {
          "sectionIndex": 4,
          "unitIndex": 4,
          "title": "Learn about Xi'an history",
          "activityPattern": [],
          "activities": 40
        },
        {
          "sectionIndex": 4,
          "unitIndex": 4,
          "title": "Share past travel mishaps",
          "activityPattern": [],
          "activities": 41
        },
        {
          "sectionIndex": 4,
          "unitIndex": 4,
          "title": "Join a sports training",
          "activityPattern": [],
          "activities": 42
        },
        {
          "sectionIndex": 4,
          "unitIndex": 4,
          "title": "Describe animals at zoo",
          "activityPattern": [],
          "activities": 43
        },
        {
          "sectionIndex": 4,
          "unitIndex": 4,
          "title": "Describe furniture condition",
          "activityPattern": [],
          "activities": 44
        },
        {
          "sectionIndex": 4,
          "unitIndex": 4,
          "title": "Invite friends to a celebration",
          "activityPattern": [],
          "activities": 45
        },
        {
          "sectionIndex": 4,
          "unitIndex": 4,
          "title": "Discuss favorite movie moments",
          "activityPattern": [],
          "activities": 46
        },
        {
          "sectionIndex": 4,
          "unitIndex": 4,
          "title": "Describe a strange noise",
          "activityPattern": [],
          "activities": 47
        },
        {
          "sectionIndex": 4,
          "unitIndex": 4,
          "title": "Discuss shopping during sales",
          "activityPattern": [],
          "activities": 48
        },
        {
          "sectionIndex": 4,
          "unitIndex": 4,
          "title": "Introduce yourself to neighbors",
          "activityPattern": [],
          "activities": 49
        },
        {
          "sectionIndex": 4,
          "unitIndex": 4,
          "title": "Communicate with colleagues remotely",
          "activityPattern": [],
          "activities": 50
        },
        {
          "sectionIndex": 4,
          "unitIndex": 4,
          "title": "Schedule a doctor's appointment",
          "activityPattern": [],
          "activities": 51
        },
        {
          "sectionIndex": 4,
          "unitIndex": 4,
          "title": "Discuss team building activities",
          "activityPattern": [],
          "activities": 52
        },
        {
          "sectionIndex": 4,
          "unitIndex": 4,
          "title": "Discuss books at a club",
          "activityPattern": [],
          "activities": 53
        },
        {
          "sectionIndex": 4,
          "unitIndex": 4,
          "title": "Open a bank account",
          "activityPattern": [],
          "activities": 54
        },
        {
          "sectionIndex": 4,
          "unitIndex": 4,
          "title": "Discuss family dinner traditions",
          "activityPattern": [],
          "activities": 55
        },
        {
          "sectionIndex": 4,
          "unitIndex": 4,
          "title": "Decide on theme park activities",
          "activityPattern": [],
          "activities": 56
        },
        {
          "sectionIndex": 4,
          "unitIndex": 4,
          "title": "Discuss business changes and future",
          "activityPattern": [],
          "activities": 57
        },
        {
          "sectionIndex": 4,
          "unitIndex": 4,
          "title": "Interview a celebrity",
          "activityPattern": [],
          "activities": 58
        },
        {
          "sectionIndex": 4,
          "unitIndex": 4,
          "title": "Call the police",
          "activityPattern": [],
          "activities": 59
        },
        {
          "sectionIndex": 4,
          "unitIndex": 4,
          "title": "Discuss different cultural backgrounds",
          "activityPattern": [
            2025,
            11,
            13
          ],
          "activities": 2049
        }
      ]
    }
  ]
}