{
  "meta": {
    "key": "zhfpl130",
    "courseTitle": "Polish → Chinese",
    "scrapedAt": "2026-01-26T02:42:01.712Z",
    "sourceHash": "sha256:edd1a989936e51d8",
    "fromLang": "Polish",
    "toLang": "Chinese",
    "fromCode": "pl",
    "toCode": "zh",
    "level": "CEFR INTRO",
    "levelShort": "INTRO",
    "detailHref": "https://duolingodata.com/dat/zhfpl130.html",
    "detailHrefHash": "sha256:c5c862d10a8b2de1",
    "scrapeWarnings": [],
    "schemaVersion": "1.0.0"
  },
  "totals": {
    "sections": 4,
    "activities": 4798,
    "units": 130
  },
  "sections": [
    {
      "sectionIndex": 1,
      "unitCount": 10,
      "title": "CEFR Intro:",
      "rawTitle": "CEFR Intro:",
      "cefr": "INTRO:",
      "units": [
        {
          "sectionIndex": 1,
          "unitIndex": 1,
          "title": "Nazwij jedzenie i napoje",
          "activityPattern": [],
          "activities": 1
        },
        {
          "sectionIndex": 1,
          "unitIndex": 1,
          "title": "Rozmawiaj o narodowościach",
          "activityPattern": [],
          "activities": 2
        },
        {
          "sectionIndex": 1,
          "unitIndex": 1,
          "title": "Rozmawiaj o zawodach",
          "activityPattern": [],
          "activities": 3
        },
        {
          "sectionIndex": 1,
          "unitIndex": 1,
          "title": "Omów swoje kursy",
          "activityPattern": [],
          "activities": 4
        },
        {
          "sectionIndex": 1,
          "unitIndex": 1,
          "title": "Używaj zaimków dzierżawczych",
          "activityPattern": [],
          "activities": 5
        },
        {
          "sectionIndex": 1,
          "unitIndex": 1,
          "title": "Opowiedz o odwiedzanych miejscach",
          "activityPattern": [],
          "activities": 6
        },
        {
          "sectionIndex": 1,
          "unitIndex": 1,
          "title": "Zamawiaj napoje",
          "activityPattern": [],
          "activities": 7
        },
        {
          "sectionIndex": 1,
          "unitIndex": 1,
          "title": "Znajdź rzeczy niezbędne w podróży",
          "activityPattern": [],
          "activities": 8
        },
        {
          "sectionIndex": 1,
          "unitIndex": 1,
          "title": "Przedstaw się i omów swoje zajęcia",
          "activityPattern": [],
          "activities": 9
        },
        {
          "sectionIndex": 1,
          "unitIndex": 1,
          "title": "Omów preferencje sportowe",
          "activityPattern": [],
          "activities": 10
        }
      ]
    },
    {
      "sectionIndex": 2,
      "unitCount": 30,
      "title": ":",
      "rawTitle": "CEFR A1:",
      "cefr": "A1",
      "units": [
        {
          "sectionIndex": 2,
          "unitIndex": 2,
          "title": "Używaj przymiotników do opisu",
          "activityPattern": [],
          "activities": 1
        },
        {
          "sectionIndex": 2,
          "unitIndex": 2,
          "title": "Odkrywaj Pekin",
          "activityPattern": [],
          "activities": 2
        },
        {
          "sectionIndex": 2,
          "unitIndex": 2,
          "title": "Używaj partykuł sugestii",
          "activityPattern": [],
          "activities": 3
        },
        {
          "sectionIndex": 2,
          "unitIndex": 2,
          "title": "Używaj poleceń",
          "activityPattern": [],
          "activities": 4
        },
        {
          "sectionIndex": 2,
          "unitIndex": 2,
          "title": "Używaj czasowników modalnych",
          "activityPattern": [],
          "activities": 5
        },
        {
          "sectionIndex": 2,
          "unitIndex": 2,
          "title": "Poproś o pozwolenie",
          "activityPattern": [],
          "activities": 6
        },
        {
          "sectionIndex": 2,
          "unitIndex": 2,
          "title": "Posprzątaj i zorganizuj swój dom",
          "activityPattern": [],
          "activities": 7
        },
        {
          "sectionIndex": 2,
          "unitIndex": 2,
          "title": "Używaj czasu teraźniejszego ciągłego",
          "activityPattern": [],
          "activities": 8
        },
        {
          "sectionIndex": 2,
          "unitIndex": 2,
          "title": "Szukaj pomocy medycznej",
          "activityPattern": [],
          "activities": 9
        },
        {
          "sectionIndex": 2,
          "unitIndex": 2,
          "title": "Zaplanuj przyjęcie urodzinowe",
          "activityPattern": [],
          "activities": 10
        },
        {
          "sectionIndex": 2,
          "unitIndex": 2,
          "title": "Zapytaj o drogę na kampusie",
          "activityPattern": [],
          "activities": 11
        },
        {
          "sectionIndex": 2,
          "unitIndex": 2,
          "title": "Używaj porównań",
          "activityPattern": [],
          "activities": 12
        },
        {
          "sectionIndex": 2,
          "unitIndex": 2,
          "title": "Opowiedz o swoim dzieciństwie",
          "activityPattern": [],
          "activities": 13
        },
        {
          "sectionIndex": 2,
          "unitIndex": 2,
          "title": "Zaplanuj swoje zajęcia",
          "activityPattern": [],
          "activities": 14
        },
        {
          "sectionIndex": 2,
          "unitIndex": 2,
          "title": "Używaj wyrażeń czasu",
          "activityPattern": [],
          "activities": 15
        },
        {
          "sectionIndex": 2,
          "unitIndex": 2,
          "title": "Kupuj ubrania",
          "activityPattern": [],
          "activities": 16
        },
        {
          "sectionIndex": 2,
          "unitIndex": 2,
          "title": "Idź na koncert",
          "activityPattern": [],
          "activities": 17
        },
        {
          "sectionIndex": 2,
          "unitIndex": 2,
          "title": "Zadawaj pytania",
          "activityPattern": [],
          "activities": 18
        },
        {
          "sectionIndex": 2,
          "unitIndex": 2,
          "title": "Mów o swoich rzeczach",
          "activityPattern": [],
          "activities": 19
        },
        {
          "sectionIndex": 2,
          "unitIndex": 2,
          "title": "Wyrażaj uczucia",
          "activityPattern": [],
          "activities": 20
        },
        {
          "sectionIndex": 2,
          "unitIndex": 2,
          "title": "Rozmawiaj o pogodzie",
          "activityPattern": [],
          "activities": 21
        },
        {
          "sectionIndex": 2,
          "unitIndex": 2,
          "title": "Opowiedz o przyjaciołach",
          "activityPattern": [],
          "activities": 22
        },
        {
          "sectionIndex": 2,
          "unitIndex": 2,
          "title": "Opisz swoją codzienną rutynę",
          "activityPattern": [],
          "activities": 23
        },
        {
          "sectionIndex": 2,
          "unitIndex": 2,
          "title": "Zarządzaj codziennymi zadaniami",
          "activityPattern": [],
          "activities": 24
        },
        {
          "sectionIndex": 2,
          "unitIndex": 2,
          "title": "Kupuj online",
          "activityPattern": [],
          "activities": 25
        },
        {
          "sectionIndex": 2,
          "unitIndex": 2,
          "title": "Omów szczegóły wynajmu",
          "activityPattern": [],
          "activities": 26
        },
        {
          "sectionIndex": 2,
          "unitIndex": 2,
          "title": "Używaj dopełnień dalszych",
          "activityPattern": [],
          "activities": 27
        },
        {
          "sectionIndex": 2,
          "unitIndex": 2,
          "title": "Zapytaj o drogę",
          "activityPattern": [],
          "activities": 28
        },
        {
          "sectionIndex": 2,
          "unitIndex": 2,
          "title": "Rozmawiaj o sportowych emocjach",
          "activityPattern": [],
          "activities": 29
        },
        {
          "sectionIndex": 2,
          "unitIndex": 2,
          "title": "Radź sobie w nagłych wypadkach",
          "activityPattern": [],
          "activities": 30
        }
      ]
    },
    {
      "sectionIndex": 3,
      "unitCount": 30,
      "title": ":",
      "rawTitle": "CEFR A1:",
      "cefr": "A1",
      "units": [
        {
          "sectionIndex": 3,
          "unitIndex": 3,
          "title": "Poruszaj się po mieście",
          "activityPattern": [],
          "activities": 1
        },
        {
          "sectionIndex": 3,
          "unitIndex": 3,
          "title": "Kupuj produkty zdrowotne",
          "activityPattern": [],
          "activities": 2
        },
        {
          "sectionIndex": 3,
          "unitIndex": 3,
          "title": "Weź udział w zakończeniu studiów",
          "activityPattern": [],
          "activities": 3
        },
        {
          "sectionIndex": 3,
          "unitIndex": 3,
          "title": "Zgłoś problem",
          "activityPattern": [],
          "activities": 4
        },
        {
          "sectionIndex": 3,
          "unitIndex": 3,
          "title": "Studiuj za granicą",
          "activityPattern": [],
          "activities": 5
        },
        {
          "sectionIndex": 3,
          "unitIndex": 3,
          "title": "Rozmawiaj o filmach",
          "activityPattern": [],
          "activities": 6
        },
        {
          "sectionIndex": 3,
          "unitIndex": 3,
          "title": "Używaj wyrażeń czasu",
          "activityPattern": [],
          "activities": 7
        },
        {
          "sectionIndex": 3,
          "unitIndex": 3,
          "title": "Poproś o wyjaśnienie",
          "activityPattern": [],
          "activities": 8
        },
        {
          "sectionIndex": 3,
          "unitIndex": 3,
          "title": "Poznaj nowych ludzi",
          "activityPattern": [],
          "activities": 9
        },
        {
          "sectionIndex": 3,
          "unitIndex": 3,
          "title": "Bierz udział w aktywnościach",
          "activityPattern": [],
          "activities": 10
        },
        {
          "sectionIndex": 3,
          "unitIndex": 3,
          "title": "Twórz pytania typu „tak/nie”",
          "activityPattern": [],
          "activities": 11
        },
        {
          "sectionIndex": 3,
          "unitIndex": 3,
          "title": "Używaj porównań",
          "activityPattern": [],
          "activities": 12
        },
        {
          "sectionIndex": 3,
          "unitIndex": 3,
          "title": "Oceń jedzenie i napoje",
          "activityPattern": [],
          "activities": 13
        },
        {
          "sectionIndex": 3,
          "unitIndex": 3,
          "title": "Kupuj artykuły spożywcze",
          "activityPattern": [],
          "activities": 14
        },
        {
          "sectionIndex": 3,
          "unitIndex": 3,
          "title": "Używaj przepisów do gotowania",
          "activityPattern": [],
          "activities": 15
        },
        {
          "sectionIndex": 3,
          "unitIndex": 3,
          "title": "Baw się na festiwalu muzycznym",
          "activityPattern": [],
          "activities": 16
        },
        {
          "sectionIndex": 3,
          "unitIndex": 3,
          "title": "Spotkaj się z przyjaciółmi",
          "activityPattern": [],
          "activities": 17
        },
        {
          "sectionIndex": 3,
          "unitIndex": 3,
          "title": "Twórz zdania złożone z kontrastem",
          "activityPattern": [],
          "activities": 18
        },
        {
          "sectionIndex": 3,
          "unitIndex": 3,
          "title": "Urządź swój dom",
          "activityPattern": [],
          "activities": 19
        },
        {
          "sectionIndex": 3,
          "unitIndex": 3,
          "title": "Rozwiązuj problemy w pracy",
          "activityPattern": [],
          "activities": 20
        },
        {
          "sectionIndex": 3,
          "unitIndex": 3,
          "title": "Podkreślaj szczegóły przeszłych wydarzeń",
          "activityPattern": [],
          "activities": 21
        },
        {
          "sectionIndex": 3,
          "unitIndex": 3,
          "title": "Opowiedz historię swojego życia",
          "activityPattern": [],
          "activities": 22
        },
        {
          "sectionIndex": 3,
          "unitIndex": 3,
          "title": "Poruszaj się po nowym mieście",
          "activityPattern": [],
          "activities": 23
        },
        {
          "sectionIndex": 3,
          "unitIndex": 3,
          "title": "Omów sprawy osobiste",
          "activityPattern": [],
          "activities": 24
        },
        {
          "sectionIndex": 3,
          "unitIndex": 3,
          "title": "Rozmawiaj o hobby z sąsiadami",
          "activityPattern": [],
          "activities": 25
        },
        {
          "sectionIndex": 3,
          "unitIndex": 3,
          "title": "Twórz zdania złożone ze spójnikami",
          "activityPattern": [],
          "activities": 26
        },
        {
          "sectionIndex": 3,
          "unitIndex": 3,
          "title": "Poruszaj się po centrum handlowym",
          "activityPattern": [],
          "activities": 27
        },
        {
          "sectionIndex": 3,
          "unitIndex": 3,
          "title": "Radź sobie w nagłych wypadkach",
          "activityPattern": [],
          "activities": 28
        },
        {
          "sectionIndex": 3,
          "unitIndex": 3,
          "title": "Wymyślaj wymówki",
          "activityPattern": [],
          "activities": 29
        },
        {
          "sectionIndex": 3,
          "unitIndex": 3,
          "title": "Załatwiaj sprawy",
          "activityPattern": [],
          "activities": 30
        }
      ]
    },
    {
      "sectionIndex": 4,
      "unitCount": 60,
      "title": ":",
      "rawTitle": "CEFR A2:",
      "cefr": "A2",
      "units": [
        {
          "sectionIndex": 4,
          "unitIndex": 4,
          "title": "Opowiedz o ciężkim tygodniu",
          "activityPattern": [],
          "activities": 1
        },
        {
          "sectionIndex": 4,
          "unitIndex": 4,
          "title": "Wspominaj szkolne czasy",
          "activityPattern": [],
          "activities": 2
        },
        {
          "sectionIndex": 4,
          "unitIndex": 4,
          "title": "Opisz dzień bez elektroniki",
          "activityPattern": [],
          "activities": 3
        },
        {
          "sectionIndex": 4,
          "unitIndex": 4,
          "title": "Pociesz zestresowanego przyjaciela",
          "activityPattern": [],
          "activities": 4
        },
        {
          "sectionIndex": 4,
          "unitIndex": 4,
          "title": "Świętuj tradycyjne chińskie festiwale",
          "activityPattern": [],
          "activities": 5
        },
        {
          "sectionIndex": 4,
          "unitIndex": 4,
          "title": "Kupuj na festiwalowych wyprzedażach",
          "activityPattern": [],
          "activities": 6
        },
        {
          "sectionIndex": 4,
          "unitIndex": 4,
          "title": "Opisz nieudaną wizytę w restauracji",
          "activityPattern": [],
          "activities": 7
        },
        {
          "sectionIndex": 4,
          "unitIndex": 4,
          "title": "Omów szczegóły projektu klienta",
          "activityPattern": [],
          "activities": 8
        },
        {
          "sectionIndex": 4,
          "unitIndex": 4,
          "title": "Używaj kuchennego słownictwa",
          "activityPattern": [],
          "activities": 9
        },
        {
          "sectionIndex": 4,
          "unitIndex": 4,
          "title": "Poproś o radę dot. wymiany studenckiej",
          "activityPattern": [],
          "activities": 10
        },
        {
          "sectionIndex": 4,
          "unitIndex": 4,
          "title": "Opisz wypadki z podróży",
          "activityPattern": [],
          "activities": 11
        },
        {
          "sectionIndex": 4,
          "unitIndex": 4,
          "title": "Dzwoń do domu, będąc w podróży",
          "activityPattern": [],
          "activities": 12
        },
        {
          "sectionIndex": 4,
          "unitIndex": 4,
          "title": "Rozwiąż biurową zagadkę",
          "activityPattern": [],
          "activities": 13
        },
        {
          "sectionIndex": 4,
          "unitIndex": 4,
          "title": "Opisuj dzieła sztuki",
          "activityPattern": [],
          "activities": 14
        },
        {
          "sectionIndex": 4,
          "unitIndex": 4,
          "title": "Twórz vlogi o podróżach",
          "activityPattern": [],
          "activities": 15
        },
        {
          "sectionIndex": 4,
          "unitIndex": 4,
          "title": "Spisz postanowienia noworoczne",
          "activityPattern": [],
          "activities": 16
        },
        {
          "sectionIndex": 4,
          "unitIndex": 4,
          "title": "Omów oceny zespołu",
          "activityPattern": [],
          "activities": 17
        },
        {
          "sectionIndex": 4,
          "unitIndex": 4,
          "title": "Porównaj występy na festiwalu sztuki",
          "activityPattern": [],
          "activities": 18
        },
        {
          "sectionIndex": 4,
          "unitIndex": 4,
          "title": "Prowadź badania do szkoły",
          "activityPattern": [],
          "activities": 19
        },
        {
          "sectionIndex": 4,
          "unitIndex": 4,
          "title": "Zadawaj pytania w podróży",
          "activityPattern": [],
          "activities": 20
        },
        {
          "sectionIndex": 4,
          "unitIndex": 4,
          "title": "Omawiaj ludzi i wydarzenia",
          "activityPattern": [],
          "activities": 21
        },
        {
          "sectionIndex": 4,
          "unitIndex": 4,
          "title": "Rozmawiaj o oświadczynach",
          "activityPattern": [],
          "activities": 22
        },
        {
          "sectionIndex": 4,
          "unitIndex": 4,
          "title": "Zadzwoń do rodziców",
          "activityPattern": [],
          "activities": 23
        },
        {
          "sectionIndex": 4,
          "unitIndex": 4,
          "title": "Zaplanuj fajny wieczór",
          "activityPattern": [],
          "activities": 24
        },
        {
          "sectionIndex": 4,
          "unitIndex": 4,
          "title": "Zaplanuj wspólną podróż",
          "activityPattern": [],
          "activities": 25
        },
        {
          "sectionIndex": 4,
          "unitIndex": 4,
          "title": "Omawiaj zdrowe wybory życiowe",
          "activityPattern": [],
          "activities": 26
        },
        {
          "sectionIndex": 4,
          "unitIndex": 4,
          "title": "Zorganizuj parapetówkę",
          "activityPattern": [],
          "activities": 27
        },
        {
          "sectionIndex": 4,
          "unitIndex": 4,
          "title": "Rozmawiaj o rodzinnym albumie",
          "activityPattern": [],
          "activities": 28
        },
        {
          "sectionIndex": 4,
          "unitIndex": 4,
          "title": "Dyskutuj o ulubionych celebrytach",
          "activityPattern": [],
          "activities": 29
        },
        {
          "sectionIndex": 4,
          "unitIndex": 4,
          "title": "Omów oceny swojego dziecka",
          "activityPattern": [],
          "activities": 30
        },
        {
          "sectionIndex": 4,
          "unitIndex": 4,
          "title": "Porównaj wieś dawniej i dziś",
          "activityPattern": [],
          "activities": 31
        },
        {
          "sectionIndex": 4,
          "unitIndex": 4,
          "title": "Rób zakupy w supermarkecie",
          "activityPattern": [],
          "activities": 32
        },
        {
          "sectionIndex": 4,
          "unitIndex": 4,
          "title": "Omów ulubione programy TV",
          "activityPattern": [],
          "activities": 33
        },
        {
          "sectionIndex": 4,
          "unitIndex": 4,
          "title": "Negocjuj kupno domu",
          "activityPattern": [],
          "activities": 34
        },
        {
          "sectionIndex": 4,
          "unitIndex": 4,
          "title": "Omawiaj uczucia z przyjaciółmi",
          "activityPattern": [],
          "activities": 35
        },
        {
          "sectionIndex": 4,
          "unitIndex": 4,
          "title": "Omów swój tygodniowy grafik",
          "activityPattern": [],
          "activities": 36
        },
        {
          "sectionIndex": 4,
          "unitIndex": 4,
          "title": "Poznawaj chińskie miasta",
          "activityPattern": [],
          "activities": 37
        },
        {
          "sectionIndex": 4,
          "unitIndex": 4,
          "title": "Opisz lekarzowi objawy",
          "activityPattern": [],
          "activities": 38
        },
        {
          "sectionIndex": 4,
          "unitIndex": 4,
          "title": "Odnów kontakt ze znajomymi",
          "activityPattern": [],
          "activities": 39
        },
        {
          "sectionIndex": 4,
          "unitIndex": 4,
          "title": "Poznaj historię Xi'an",
          "activityPattern": [],
          "activities": 40
        },
        {
          "sectionIndex": 4,
          "unitIndex": 4,
          "title": "Podziel się wpadkami z podróży",
          "activityPattern": [],
          "activities": 41
        },
        {
          "sectionIndex": 4,
          "unitIndex": 4,
          "title": "Weź udział w treningu sportowym",
          "activityPattern": [],
          "activities": 42
        },
        {
          "sectionIndex": 4,
          "unitIndex": 4,
          "title": "Opisz zwierzęta w zoo",
          "activityPattern": [],
          "activities": 43
        },
        {
          "sectionIndex": 4,
          "unitIndex": 4,
          "title": "Opisz stan mebli",
          "activityPattern": [],
          "activities": 44
        },
        {
          "sectionIndex": 4,
          "unitIndex": 4,
          "title": "Zaproś znajomych na świętowanie",
          "activityPattern": [],
          "activities": 45
        },
        {
          "sectionIndex": 4,
          "unitIndex": 4,
          "title": "Omów ulubione momenty filmowe",
          "activityPattern": [],
          "activities": 46
        },
        {
          "sectionIndex": 4,
          "unitIndex": 4,
          "title": "Opisz dziwny hałas",
          "activityPattern": [],
          "activities": 47
        },
        {
          "sectionIndex": 4,
          "unitIndex": 4,
          "title": "Rozmawiaj o zakupach na wyprzedażach",
          "activityPattern": [],
          "activities": 48
        },
        {
          "sectionIndex": 4,
          "unitIndex": 4,
          "title": "Przedstaw się sąsiadom",
          "activityPattern": [],
          "activities": 49
        },
        {
          "sectionIndex": 4,
          "unitIndex": 4,
          "title": "Komunikuj się zdalnie z kolegami",
          "activityPattern": [],
          "activities": 50
        },
        {
          "sectionIndex": 4,
          "unitIndex": 4,
          "title": "Umów wizytę u lekarza",
          "activityPattern": [],
          "activities": 51
        },
        {
          "sectionIndex": 4,
          "unitIndex": 4,
          "title": "Rozmawiaj o zajęciach integracyjnych",
          "activityPattern": [],
          "activities": 52
        },
        {
          "sectionIndex": 4,
          "unitIndex": 4,
          "title": "Dyskutuj w klubie książki",
          "activityPattern": [],
          "activities": 53
        },
        {
          "sectionIndex": 4,
          "unitIndex": 4,
          "title": "Otwórz konto w banku",
          "activityPattern": [],
          "activities": 54
        },
        {
          "sectionIndex": 4,
          "unitIndex": 4,
          "title": "Omów tradycje rodzinnych kolacji",
          "activityPattern": [],
          "activities": 55
        },
        {
          "sectionIndex": 4,
          "unitIndex": 4,
          "title": "Wybierz atrakcje w parku rozrywki",
          "activityPattern": [],
          "activities": 56
        },
        {
          "sectionIndex": 4,
          "unitIndex": 4,
          "title": "Omów zmiany i przyszłość firmy",
          "activityPattern": [],
          "activities": 57
        },
        {
          "sectionIndex": 4,
          "unitIndex": 4,
          "title": "Przeprowadź wywiad z kimś sławnym",
          "activityPattern": [],
          "activities": 58
        },
        {
          "sectionIndex": 4,
          "unitIndex": 4,
          "title": "Zadzwoń na policję",
          "activityPattern": [],
          "activities": 59
        },
        {
          "sectionIndex": 4,
          "unitIndex": 4,
          "title": "Dyskutuj o różnych kulturach",
          "activityPattern": [
            2025,
            10,
            8
          ],
          "activities": 2043
        }
      ]
    }
  ]
}